{"name":"Bass","tuning":[-2,-2,-2,-2,0,0],"capo":0,"notes":[{"t":11.427,"s":1,"f":7,"sus":0.0,"sl":-1,"slu":-1,"bn":0,"ho":false,"po":false,"hm":false,"hp":false,"pm":false,"mt":false,"tr":false,"ac":false,"tp":false},{"t":11.695,"s":1,"f":7,"sus":0.0,"sl":-1,"slu":-1,"bn":0,"ho":false,"po":false,"hm":false,"hp":false,"pm":false,"mt":false,"tr":false,"ac":false,"tp":false},{"t":11.953,"s":1,"f":8,"sus":0.0,"sl":-1,"slu":-1,"bn":0,"ho":false,"po":false,"hm":false,"hp":false,"pm":false,"mt":false,"tr":false,"ac":false,"tp":false},{"t":12.203,"s":1,"f":9,"sus":0.497,"sl":-1,"slu":-1,"bn":0,"ho":false,"po":false,"hm":false,"hp":false,"pm":false,"mt":false,"tr":false,"ac":false,"tp":false},{"t":12.703,"s":2,"f":7,"sus":0.0,"sl":-1,"slu":-1,"bn":0,"ho":false,"po":false,"hm":false,"hp":false,"pm":false,"mt":false,"tr":false,"ac":false,"tp":false},{"t":12.953,"s":1,"f":9,"sus":0.0,"sl":-1,"slu":-1,"bn":0,"ho":false,"po":false,"hm":false,"hp":false,"pm":false,"mt":false,"tr":false,"ac":false,"tp":false},{"t":13.203,"s":2,"f":7,"sus":0.0,"sl":-1,"slu":-1,"bn":0,"ho":false,"po":false,"hm":false,"hp":false,"pm":false,"mt":false,"tr":false,"ac":false,"tp":false},{"t":13.453,"s":1,"f":9,"sus":0.0,"sl":-1,"slu":-1,"bn":0,"ho":false,"po":false,"hm":false,"hp":false,"pm":false,"mt":false,"tr":false,"ac":false,"tp":false},{"t":13.703,"s":1,"f":9,"sus":0.0,"sl":-1,"slu":-1,"bn":0,"ho":false,"po":false,"hm":false,"hp":false,"pm":false,"mt":false,"tr":false,"ac":false,"tp":false},{"t":13.953,"s":1,"f":8,"sus":0.0,"sl":-1,"slu":-1,"bn":0,"ho":false,"po":false,"hm":false,"hp":false,"pm":false,"mt":false,"tr":false,"ac":false,"tp":false},{"t":14.203,"s":1,"f":7,"sus":0.0,"sl":-1,"slu":-1,"bn":0,"ho":false,"po":false,"hm":false,"hp":false,"pm":false,"mt":false,"tr":false,"ac":false,"tp":false},{"t":14.453,"s":2,"f":9,"sus":0.0,"sl":-1,"slu":-1,"bn":0,"ho":false,"po":false,"hm":false,"hp":false,"pm":false,"mt":false,"tr":false,"ac":false,"tp":false},{"t":14.703,"s":1,"f":7,"sus":0.0,"sl":-1,"slu":-1,"bn":0,"ho":false,"po":false,"hm":false,"hp":false,"pm":false,"mt":false,"tr":false,"ac":false,"tp":false},{"t":14.953,"s":1,"f":7,"sus":0.497,"sl":-1,"slu":-1,"bn":0,"ho":false,"po":false,"hm":false,"hp":false,"pm":false,"mt":false,"tr":false,"ac":false,"tp":false},{"t":15.453,"s":2,"f":9,"sus":0.0,"sl":-1,"slu":-1,"bn":0,"ho":false,"po":false,"hm":false,"hp":false,"pm":false,"mt":false,"tr":false,"ac":false,"tp":false},{"t":15.703,"s":1,"f":7,"sus":0.0,"sl":-1,"slu":-1,"bn":0,"ho":false,"po":false,"hm":false,"hp":false,"pm":false,"mt":false,"tr":false,"ac":false,"tp":false},{"t":15.953,"s":1,"f":8,"sus":0.0,"sl":-1,"slu":-1,"bn":0,"ho":false,"po":false,"hm":false,"hp":false,"pm":false,"mt":false,"tr":false,"ac":false,"tp":false},{"t":16.203,"s":1,"f":9,"sus":0.497,"sl":-1,"slu":-1,"bn":0,"ho":false,"po":false,"hm":false,"hp":false,"pm":false,"mt":false,"tr":false,"ac":false,"tp":false},{"t":16.703,"s":2,"f":7,"sus":0.0,"sl":-1,"slu":-1,"bn":0,"ho":false,"po":false,"hm":false,"hp":false,"pm":false,"mt":false,"tr":false,"ac":false,"tp":false},{"t":16.953,"s":1,"f":9,"sus":0.0,"sl":-1,"slu":-1,"bn":0,"ho":false,"po":false,"hm":false,"hp":false,"pm":false,"mt":false,"tr":false,"ac":false,"tp":false},{"t":17.203,"s":2,"f":7,"sus":0.0,"sl":-1,"slu":-1,"bn":0,"ho":false,"po":false,"hm":false,"hp":false,"pm":false,"mt":false,"tr":false,"ac":false,"tp":false},{"t":17.453,"s":1,"f":9,"sus":0.0,"sl":-1,"slu":-1,"bn":0,"ho":false,"po":false,"hm":false,"hp":false,"pm":false,"mt":false,"tr":false,"ac":false,"tp":false},{"t":17.703,"s":1,"f":9,"sus":0.0,"sl":-1,"slu":-1,"bn":0,"ho":false,"po":false,"hm":false,"hp":false,"pm":false,"mt":false,"tr":false,"ac":false,"tp":false},{"t":17.953,"s":1,"f":8,"sus":0.0,"sl":-1,"slu":-1,"bn":0,"ho":false,"po":false,"hm":false,"hp":false,"pm":false,"mt":false,"tr":false,"ac":false,"tp":false},{"t":18.203,"s":1,"f":7,"sus":0.0,"sl":-1,"slu":-1,"bn":0,"ho":false,"po":false,"hm":false,"hp":false,"pm":false,"mt":false,"tr":false,"ac":false,"tp":false},{"t":18.453,"s":2,"f":9,"sus":0.0,"sl":-1,"slu":-1,"bn":0,"ho":false,"po":false,"hm":false,"hp":false,"pm":false,"mt":false,"tr":false,"ac":false,"tp":false},{"t":18.703,"s":1,"f":7,"sus":0.0,"sl":-1,"slu":-1,"bn":0,"ho":false,"po":false,"hm":false,"hp":false,"pm":false,"mt":false,"tr":false,"ac":false,"tp":false},{"t":18.953,"s":1,"f":7,"sus":0.497,"sl":-1,"slu":-1,"bn":0,"ho":false,"po":false,"hm":false,"hp":false,"pm":false,"mt":false,"tr":false,"ac":false,"tp":false},{"t":19.453,"s":2,"f":9,"sus":0.0,"sl":-1,"slu":-1,"bn":0,"ho":false,"po":false,"hm":false,"hp":false,"pm":false,"mt":false,"tr":false,"ac":false,"tp":false},{"t":19.703,"s":1,"f":7,"sus":0.0,"sl":-1,"slu":-1,"bn":0,"ho":false,"po":false,"hm":false,"hp":false,"pm":false,"mt":false,"tr":false,"ac":false,"tp":false},{"t":19.953,"s":1,"f":8,"sus":0.0,"sl":-1,"slu":-1,"bn":0,"ho":false,"po":false,"hm":false,"hp":false,"pm":false,"mt":false,"tr":false,"ac":false,"tp":false},{"t":20.203,"s":1,"f":9,"sus":0.497,"sl":-1,"slu":-1,"bn":0,"ho":false,"po":false,"hm":false,"hp":false,"pm":false,"mt":false,"tr":false,"ac":false,"tp":false},{"t":20.703,"s":2,"f":7,"sus":0.0,"sl":-1,"slu":-1,"bn":0,"ho":false,"po":false,"hm":false,"hp":false,"pm":false,"mt":false,"tr":false,"ac":false,"tp":false},{"t":20.953,"s":1,"f":9,"sus":0.0,"sl":-1,"slu":-1,"bn":0,"ho":false,"po":false,"hm":false,"hp":false,"pm":false,"mt":false,"tr":false,"ac":false,"tp":false},{"t":21.203,"s":2,"f":7,"sus":0.0,"sl":-1,"slu":-1,"bn":0,"ho":false,"po":false,"hm":false,"hp":false,"pm":false,"mt":false,"tr":false,"ac":false,"tp":false},{"t":21.453,"s":1,"f":9,"sus":0.0,"sl":-1,"slu":-1,"bn":0,"ho":false,"po":false,"hm":false,"hp":false,"pm":false,"mt":false,"tr":false,"ac":false,"tp":false},{"t":21.703,"s":1,"f":9,"sus":0.0,"sl":-1,"slu":-1,"bn":0,"ho":false,"po":false,"hm":false,"hp":false,"pm":false,"mt":false,"tr":false,"ac":false,"tp":false},{"t":21.953,"s":1,"f":8,"sus":0.0,"sl":-1,"slu":-1,"bn":0,"ho":false,"po":false,"hm":false,"hp":false,"pm":false,"mt":false,"tr":false,"ac":false,"tp":false},{"t":22.203,"s":1,"f":7,"sus":0.0,"sl":-1,"slu":-1,"bn":0,"ho":false,"po":false,"hm":false,"hp":false,"pm":false,"mt":false,"tr":false,"ac":false,"tp":false},{"t":22.453,"s":2,"f":9,"sus":0.0,"sl":-1,"slu":-1,"bn":0,"ho":false,"po":false,"hm":false,"hp":false,"pm":false,"mt":false,"tr":false,"ac":false,"tp":false},{"t":22.703,"s":1,"f":7,"sus":0.0,"sl":-1,"slu":-1,"bn":0,"ho":false,"po":false,"hm":false,"hp":false,"pm":false,"mt":false,"tr":false,"ac":false,"tp":false},{"t":22.953,"s":1,"f":7,"sus":0.497,"sl":-1,"slu":-1,"bn":0,"ho":false,"po":false,"hm":false,"hp":false,"pm":false,"mt":false,"tr":false,"ac":false,"tp":false},{"t":23.453,"s":2,"f":9,"sus":0.0,"sl":-1,"slu":-1,"bn":0,"ho":false,"po":false,"hm":false,"hp":false,"pm":false,"mt":false,"tr":false,"ac":false,"tp":false},{"t":23.703,"s":1,"f":7,"sus":0.0,"sl":-1,"slu":-1,"bn":0,"ho":false,"po":false,"hm":false,"hp":false,"pm":false,"mt":false,"tr":false,"ac":false,"tp":false},{"t":23.953,"s":1,"f":8,"sus":0.0,"sl":-1,"slu":-1,"bn":0,"ho":false,"po":false,"hm":false,"hp":false,"pm":false,"mt":false,"tr":false,"ac":false,"tp":false},{"t":24.203,"s":1,"f":9,"sus":0.497,"sl":-1,"slu":-1,"bn":0,"ho":false,"po":false,"hm":false,"hp":false,"pm":false,"mt":false,"tr":false,"ac":false,"tp":false},{"t":24.703,"s":2,"f":7,"sus":0.0,"sl":-1,"slu":-1,"bn":0,"ho":false,"po":false,"hm":false,"hp":false,"pm":false,"mt":false,"tr":false,"ac":false,"tp":false},{"t":24.953,"s":1,"f":9,"sus":0.0,"sl":-1,"slu":-1,"bn":0,"ho":false,"po":false,"hm":false,"hp":false,"pm":false,"mt":false,"tr":false,"ac":false,"tp":false},{"t":25.203,"s":2,"f":7,"sus":0.0,"sl":-1,"slu":-1,"bn":0,"ho":false,"po":false,"hm":false,"hp":false,"pm":false,"mt":false,"tr":false,"ac":false,"tp":false},{"t":25.453,"s":1,"f":9,"sus":0.0,"sl":-1,"slu":-1,"bn":0,"ho":false,"po":false,"hm":false,"hp":false,"pm":false,"mt":false,"tr":false,"ac":false,"tp":false},{"t":25.703,"s":1,"f":9,"sus":0.0,"sl":-1,"slu":-1,"bn":0,"ho":false,"po":false,"hm":false,"hp":false,"pm":false,"mt":false,"tr":false,"ac":false,"tp":false},{"t":25.953,"s":1,"f":8,"sus":0.0,"sl":-1,"slu":-1,"bn":0,"ho":false,"po":false,"hm":false,"hp":false,"pm":false,"mt":false,"tr":false,"ac":false,"tp":false},{"t":26.203,"s":1,"f":7,"sus":0.0,"sl":-1,"slu":-1,"bn":0,"ho":false,"po":false,"hm":false,"hp":false,"pm":false,"mt":false,"tr":false,"ac":false,"tp":false},{"t":26.453,"s":2,"f":9,"sus":0.0,"sl":-1,"slu":-1,"bn":0,"ho":false,"po":false,"hm":false,"hp":false,"pm":false,"mt":false,"tr":false,"ac":false,"tp":false},{"t":26.703,"s":1,"f":7,"sus":0.0,"sl":-1,"slu":-1,"bn":0,"ho":false,"po":false,"hm":false,"hp":false,"pm":false,"mt":false,"tr":false,"ac":false,"tp":false},{"t":26.953,"s":1,"f":7,"sus":0.497,"sl":-1,"slu":-1,"bn":0,"ho":false,"po":false,"hm":false,"hp":false,"pm":false,"mt":false,"tr":false,"ac":false,"tp":false},{"t":27.453,"s":2,"f":9,"sus":0.0,"sl":-1,"slu":-1,"bn":0,"ho":false,"po":false,"hm":false,"hp":false,"pm":false,"mt":false,"tr":false,"ac":false,"tp":false},{"t":27.703,"s":1,"f":7,"sus":0.0,"sl":-1,"slu":-1,"bn":0,"ho":false,"po":false,"hm":false,"hp":false,"pm":false,"mt":false,"tr":false,"ac":false,"tp":false},{"t":27.953,"s":1,"f":8,"sus":0.0,"sl":-1,"slu":-1,"bn":0,"ho":false,"po":false,"hm":false,"hp":false,"pm":false,"mt":false,"tr":false,"ac":false,"tp":false},{"t":28.203,"s":1,"f":9,"sus":0.497,"sl":-1,"slu":-1,"bn":0,"ho":false,"po":false,"hm":false,"hp":false,"pm":false,"mt":false,"tr":false,"ac":false,"tp":false},{"t":28.703,"s":2,"f":7,"sus":0.0,"sl":-1,"slu":-1,"bn":0,"ho":false,"po":false,"hm":false,"hp":false,"pm":false,"mt":false,"tr":false,"ac":false,"tp":false},{"t":28.953,"s":1,"f":9,"sus":0.0,"sl":-1,"slu":-1,"bn":0,"ho":false,"po":false,"hm":false,"hp":false,"pm":false,"mt":false,"tr":false,"ac":false,"tp":false},{"t":29.203,"s":2,"f":7,"sus":0.0,"sl":-1,"slu":-1,"bn":0,"ho":false,"po":false,"hm":false,"hp":false,"pm":false,"mt":false,"tr":false,"ac":false,"tp":false},{"t":29.453,"s":1,"f":9,"sus":0.0,"sl":-1,"slu":-1,"bn":0,"ho":false,"po":false,"hm":false,"hp":false,"pm":false,"mt":false,"tr":false,"ac":false,"tp":false},{"t":29.703,"s":1,"f":9,"sus":0.0,"sl":-1,"slu":-1,"bn":0,"ho":false,"po":false,"hm":false,"hp":false,"pm":false,"mt":false,"tr":false,"ac":false,"tp":false},{"t":29.953,"s":1,"f":8,"sus":0.0,"sl":-1,"slu":-1,"bn":0,"ho":false,"po":false,"hm":false,"hp":false,"pm":false,"mt":false,"tr":false,"ac":false,"tp":false},{"t":30.203,"s":1,"f":7,"sus":0.0,"sl":-1,"slu":-1,"bn":0,"ho":false,"po":false,"hm":false,"hp":false,"pm":false,"mt":false,"tr":false,"ac":false,"tp":false},{"t":30.453,"s":2,"f":9,"sus":0.0,"sl":-1,"slu":-1,"bn":0,"ho":false,"po":false,"hm":false,"hp":false,"pm":false,"mt":false,"tr":false,"ac":false,"tp":false},{"t":30.703,"s":1,"f":7,"sus":0.0,"sl":-1,"slu":-1,"bn":0,"ho":false,"po":false,"hm":false,"hp":false,"pm":false,"mt":false,"tr":false,"ac":false,"tp":false},{"t":30.953,"s":1,"f":7,"sus":0.497,"sl":-1,"slu":-1,"bn":0,"ho":false,"po":false,"hm":false,"hp":false,"pm":false,"mt":false,"tr":false,"ac":false,"tp":false},{"t":31.453,"s":2,"f":9,"sus":0.0,"sl":-1,"slu":-1,"bn":0,"ho":false,"po":false,"hm":false,"hp":false,"pm":false,"mt":false,"tr":false,"ac":false,"tp":false},{"t":31.703,"s":1,"f":7,"sus":0.0,"sl":-1,"slu":-1,"bn":0,"ho":false,"po":false,"hm":false,"hp":false,"pm":false,"mt":false,"tr":false,"ac":false,"tp":false},{"t":31.953,"s":1,"f":8,"sus":0.0,"sl":-1,"slu":-1,"bn":0,"ho":false,"po":false,"hm":false,"hp":false,"pm":false,"mt":false,"tr":false,"ac":false,"tp":false},{"t":32.203,"s":1,"f":9,"sus":0.497,"sl":-1,"slu":-1,"bn":0,"ho":false,"po":false,"hm":false,"hp":false,"pm":false,"mt":false,"tr":false,"ac":false,"tp":false},{"t":32.703,"s":2,"f":7,"sus":0.0,"sl":-1,"slu":-1,"bn":0,"ho":false,"po":false,"hm":false,"hp":false,"pm":false,"mt":false,"tr":false,"ac":false,"tp":false},{"t":32.953,"s":1,"f":9,"sus":0.0,"sl":-1,"slu":-1,"bn":0,"ho":false,"po":false,"hm":false,"hp":false,"pm":false,"mt":false,"tr":false,"ac":false,"tp":false},{"t":33.203,"s":2,"f":7,"sus":0.0,"sl":-1,"slu":-1,"bn":0,"ho":false,"po":false,"hm":false,"hp":false,"pm":false,"mt":false,"tr":false,"ac":false,"tp":false},{"t":33.449,"s":1,"f":9,"sus":0.0,"sl":-1,"slu":-1,"bn":0,"ho":false,"po":false,"hm":false,"hp":false,"pm":false,"mt":false,"tr":false,"ac":false,"tp":false},{"t":33.691,"s":1,"f":9,"sus":0.0,"sl":-1,"slu":-1,"bn":0,"ho":false,"po":false,"hm":false,"hp":false,"pm":false,"mt":false,"tr":false,"ac":false,"tp":false},{"t":33.937,"s":1,"f":8,"sus":0.0,"sl":-1,"slu":-1,"bn":0,"ho":false,"po":false,"hm":false,"hp":false,"pm":false,"mt":false,"tr":false,"ac":false,"tp":false},{"t":34.187,"s":1,"f":7,"sus":0.0,"sl":-1,"slu":-1,"bn":0,"ho":false,"po":false,"hm":false,"hp":false,"pm":false,"mt":false,"tr":false,"ac":false,"tp":false},{"t":34.437,"s":2,"f":9,"sus":0.0,"sl":-1,"slu":-1,"bn":0,"ho":false,"po":false,"hm":false,"hp":false,"pm":false,"mt":false,"tr":false,"ac":false,"tp":false},{"t":34.687,"s":1,"f":7,"sus":0.0,"sl":-1,"slu":-1,"bn":0,"ho":false,"po":false,"hm":false,"hp":false,"pm":false,"mt":false,"tr":false,"ac":false,"tp":false},{"t":34.937,"s":1,"f":7,"sus":0.497,"sl":-1,"slu":-1,"bn":0,"ho":false,"po":false,"hm":false,"hp":false,"pm":false,"mt":false,"tr":false,"ac":false,"tp":false},{"t":35.437,"s":2,"f":9,"sus":0.0,"sl":-1,"slu":-1,"bn":0,"ho":false,"po":false,"hm":false,"hp":false,"pm":false,"mt":false,"tr":false,"ac":false,"tp":false},{"t":35.687,"s":1,"f":7,"sus":0.0,"sl":-1,"slu":-1,"bn":0,"ho":false,"po":false,"hm":false,"hp":false,"pm":false,"mt":false,"tr":false,"ac":false,"tp":false},{"t":35.937,"s":1,"f":8,"sus":0.0,"sl":-1,"slu":-1,"bn":0,"ho":false,"po":false,"hm":false,"hp":false,"pm":false,"mt":false,"tr":false,"ac":false,"tp":false},{"t":36.187,"s":1,"f":9,"sus":0.497,"sl":-1,"slu":-1,"bn":0,"ho":false,"po":false,"hm":false,"hp":false,"pm":false,"mt":false,"tr":false,"ac":false,"tp":false},{"t":36.687,"s":2,"f":7,"sus":0.0,"sl":-1,"slu":-1,"bn":0,"ho":false,"po":false,"hm":false,"hp":false,"pm":false,"mt":false,"tr":false,"ac":false,"tp":false},{"t":36.937,"s":1,"f":9,"sus":0.0,"sl":-1,"slu":-1,"bn":0,"ho":false,"po":false,"hm":false,"hp":false,"pm":false,"mt":false,"tr":false,"ac":false,"tp":false},{"t":37.187,"s":2,"f":7,"sus":0.0,"sl":-1,"slu":-1,"bn":0,"ho":false,"po":false,"hm":false,"hp":false,"pm":false,"mt":false,"tr":false,"ac":false,"tp":false},{"t":37.437,"s":1,"f":9,"sus":0.0,"sl":-1,"slu":-1,"bn":0,"ho":false,"po":false,"hm":false,"hp":false,"pm":false,"mt":false,"tr":false,"ac":false,"tp":false},{"t":37.687,"s":1,"f":9,"sus":0.0,"sl":-1,"slu":-1,"bn":0,"ho":false,"po":false,"hm":false,"hp":false,"pm":false,"mt":false,"tr":false,"ac":false,"tp":false},{"t":37.937,"s":1,"f":8,"sus":0.0,"sl":-1,"slu":-1,"bn":0,"ho":false,"po":false,"hm":false,"hp":false,"pm":false,"mt":false,"tr":false,"ac":false,"tp":false},{"t":38.187,"s":1,"f":7,"sus":0.0,"sl":-1,"slu":-1,"bn":0,"ho":false,"po":false,"hm":false,"hp":false,"pm":false,"mt":false,"tr":false,"ac":false,"tp":false},{"t":38.437,"s":2,"f":9,"sus":0.0,"sl":-1,"slu":-1,"bn":0,"ho":false,"po":false,"hm":false,"hp":false,"pm":false,"mt":false,"tr":false,"ac":false,"tp":false},{"t":38.687,"s":1,"f":7,"sus":0.0,"sl":-1,"slu":-1,"bn":0,"ho":false,"po":false,"hm":false,"hp":false,"pm":false,"mt":false,"tr":false,"ac":false,"tp":false},{"t":38.937,"s":1,"f":7,"sus":0.497,"sl":-1,"slu":-1,"bn":0,"ho":false,"po":false,"hm":false,"hp":false,"pm":false,"mt":false,"tr":false,"ac":false,"tp":false},{"t":39.437,"s":2,"f":9,"sus":0.0,"sl":-1,"slu":-1,"bn":0,"ho":false,"po":false,"hm":false,"hp":false,"pm":false,"mt":false,"tr":false,"ac":false,"tp":false},{"t":39.687,"s":1,"f":7,"sus":0.0,"sl":-1,"slu":-1,"bn":0,"ho":false,"po":false,"hm":false,"hp":false,"pm":false,"mt":false,"tr":false,"ac":false,"tp":false},{"t":39.937,"s":1,"f":8,"sus":0.0,"sl":-1,"slu":-1,"bn":0,"ho":false,"po":false,"hm":false,"hp":false,"pm":false,"mt":false,"tr":false,"ac":false,"tp":false},{"t":40.187,"s":1,"f":9,"sus":0.497,"sl":-1,"slu":-1,"bn":0,"ho":false,"po":false,"hm":false,"hp":false,"pm":false,"mt":false,"tr":false,"ac":false,"tp":false},{"t":40.687,"s":2,"f":7,"sus":0.0,"sl":-1,"slu":-1,"bn":0,"ho":false,"po":false,"hm":false,"hp":false,"pm":false,"mt":false,"tr":false,"ac":false,"tp":false},{"t":40.937,"s":1,"f":9,"sus":0.0,"sl":-1,"slu":-1,"bn":0,"ho":false,"po":false,"hm":false,"hp":false,"pm":false,"mt":false,"tr":false,"ac":false,"tp":false},{"t":41.187,"s":2,"f":7,"sus":0.0,"sl":-1,"slu":-1,"bn":0,"ho":false,"po":false,"hm":false,"hp":false,"pm":false,"mt":false,"tr":false,"ac":false,"tp":false},{"t":41.437,"s":1,"f":9,"sus":0.0,"sl":-1,"slu":-1,"bn":0,"ho":false,"po":false,"hm":false,"hp":false,"pm":false,"mt":false,"tr":false,"ac":false,"tp":false},{"t":41.687,"s":1,"f":9,"sus":0.0,"sl":-1,"slu":-1,"bn":0,"ho":false,"po":false,"hm":false,"hp":false,"pm":false,"mt":false,"tr":false,"ac":false,"tp":false},{"t":41.937,"s":1,"f":8,"sus":0.0,"sl":-1,"slu":-1,"bn":0,"ho":false,"po":false,"hm":false,"hp":false,"pm":false,"mt":false,"tr":false,"ac":false,"tp":false},{"t":42.187,"s":1,"f":7,"sus":0.0,"sl":-1,"slu":-1,"bn":0,"ho":false,"po":false,"hm":false,"hp":false,"pm":false,"mt":false,"tr":false,"ac":false,"tp":false},{"t":42.437,"s":2,"f":9,"sus":0.0,"sl":-1,"slu":-1,"bn":0,"ho":false,"po":false,"hm":false,"hp":false,"pm":false,"mt":false,"tr":false,"ac":false,"tp":false},{"t":42.687,"s":1,"f":7,"sus":0.0,"sl":-1,"slu":-1,"bn":0,"ho":false,"po":false,"hm":false,"hp":false,"pm":false,"mt":false,"tr":false,"ac":false,"tp":false},{"t":42.937,"s":1,"f":7,"sus":0.493,"sl":-1,"slu":-1,"bn":0,"ho":false,"po":false,"hm":false,"hp":false,"pm":false,"mt":false,"tr":false,"ac":false,"tp":false},{"t":43.433,"s":2,"f":9,"sus":0.0,"sl":-1,"slu":-1,"bn":0,"ho":false,"po":false,"hm":false,"hp":false,"pm":false,"mt":false,"tr":false,"ac":false,"tp":false},{"t":43.675,"s":1,"f":7,"sus":0.0,"sl":-1,"slu":-1,"bn":0,"ho":false,"po":false,"hm":false,"hp":false,"pm":false,"mt":false,"tr":false,"ac":false,"tp":false},{"t":43.917,"s":1,"f":8,"sus":0.0,"sl":-1,"slu":-1,"bn":0,"ho":false,"po":false,"hm":false,"hp":false,"pm":false,"mt":false,"tr":false,"ac":false,"tp":false},{"t":44.159,"s":1,"f":9,"sus":0.481,"sl":-1,"slu":-1,"bn":0,"ho":false,"po":false,"hm":false,"hp":false,"pm":false,"mt":false,"tr":false,"ac":false,"tp":false},{"t":44.643,"s":2,"f":7,"sus":0.0,"sl":-1,"slu":-1,"bn":0,"ho":false,"po":false,"hm":false,"hp":false,"pm":false,"mt":false,"tr":false,"ac":false,"tp":false},{"t":44.891,"s":1,"f":9,"sus":0.0,"sl":-1,"slu":-1,"bn":0,"ho":false,"po":false,"hm":false,"hp":false,"pm":false,"mt":false,"tr":false,"ac":false,"tp":false},{"t":45.143,"s":2,"f":7,"sus":0.0,"sl":-1,"slu":-1,"bn":0,"ho":false,"po":false,"hm":false,"hp":false,"pm":false,"mt":false,"tr":false,"ac":false,"tp":false},{"t":45.397,"s":1,"f":9,"sus":0.0,"sl":-1,"slu":-1,"bn":0,"ho":false,"po":false,"hm":false,"hp":false,"pm":false,"mt":false,"tr":false,"ac":false,"tp":false},{"t":45.649,"s":1,"f":9,"sus":0.0,"sl":-1,"slu":-1,"bn":0,"ho":false,"po":false,"hm":false,"hp":false,"pm":false,"mt":false,"tr":false,"ac":false,"tp":false},{"t":45.903,"s":1,"f":8,"sus":0.0,"sl":-1,"slu":-1,"bn":0,"ho":false,"po":false,"hm":false,"hp":false,"pm":false,"mt":false,"tr":false,"ac":false,"tp":false},{"t":46.155,"s":1,"f":7,"sus":0.0,"sl":-1,"slu":-1,"bn":0,"ho":false,"po":false,"hm":false,"hp":false,"pm":false,"mt":false,"tr":false,"ac":false,"tp":false},{"t":46.409,"s":2,"f":9,"sus":0.0,"sl":-1,"slu":-1,"bn":0,"ho":false,"po":false,"hm":false,"hp":false,"pm":false,"mt":false,"tr":false,"ac":false,"tp":false},{"t":46.661,"s":1,"f":7,"sus":0.0,"sl":-1,"slu":-1,"bn":0,"ho":false,"po":false,"hm":false,"hp":false,"pm":false,"mt":false,"tr":false,"ac":false,"tp":false},{"t":46.915,"s":1,"f":7,"sus":0.503,"sl":-1,"slu":-1,"bn":0,"ho":false,"po":false,"hm":false,"hp":false,"pm":false,"mt":false,"tr":false,"ac":false,"tp":false},{"t":47.421,"s":2,"f":9,"sus":0.0,"sl":-1,"slu":-1,"bn":0,"ho":false,"po":false,"hm":false,"hp":false,"pm":false,"mt":false,"tr":false,"ac":false,"tp":false},{"t":47.673,"s":1,"f":7,"sus":0.0,"sl":-1,"slu":-1,"bn":0,"ho":false,"po":false,"hm":false,"hp":false,"pm":false,"mt":false,"tr":false,"ac":false,"tp":false},{"t":47.927,"s":1,"f":8,"sus":0.0,"sl":-1,"slu":-1,"bn":0,"ho":false,"po":false,"hm":false,"hp":false,"pm":false,"mt":false,"tr":false,"ac":false,"tp":false},{"t":48.179,"s":1,"f":9,"sus":0.503,"sl":-1,"slu":-1,"bn":0,"ho":false,"po":false,"hm":false,"hp":false,"pm":false,"mt":false,"tr":false,"ac":false,"tp":false},{"t":48.685,"s":2,"f":7,"sus":0.0,"sl":-1,"slu":-1,"bn":0,"ho":false,"po":false,"hm":false,"hp":false,"pm":false,"mt":false,"tr":false,"ac":false,"tp":false},{"t":48.929,"s":1,"f":9,"sus":0.0,"sl":-1,"slu":-1,"bn":0,"ho":false,"po":false,"hm":false,"hp":false,"pm":false,"mt":false,"tr":false,"ac":false,"tp":false},{"t":49.163,"s":2,"f":7,"sus":0.0,"sl":-1,"slu":-1,"bn":0,"ho":false,"po":false,"hm":false,"hp":false,"pm":false,"mt":false,"tr":false,"ac":false,"tp":false},{"t":49.405,"s":1,"f":9,"sus":0.0,"sl":-1,"slu":-1,"bn":0,"ho":false,"po":false,"hm":false,"hp":false,"pm":false,"mt":false,"tr":false,"ac":false,"tp":false},{"t":49.655,"s":1,"f":9,"sus":0.0,"sl":-1,"slu":-1,"bn":0,"ho":false,"po":false,"hm":false,"hp":false,"pm":false,"mt":false,"tr":false,"ac":false,"tp":false},{"t":49.905,"s":1,"f":8,"sus":0.0,"sl":-1,"slu":-1,"bn":0,"ho":false,"po":false,"hm":false,"hp":false,"pm":false,"mt":false,"tr":false,"ac":false,"tp":false},{"t":50.155,"s":1,"f":7,"sus":0.0,"sl":-1,"slu":-1,"bn":0,"ho":false,"po":false,"hm":false,"hp":false,"pm":false,"mt":false,"tr":false,"ac":false,"tp":false},{"t":50.405,"s":2,"f":9,"sus":0.0,"sl":-1,"slu":-1,"bn":0,"ho":false,"po":false,"hm":false,"hp":false,"pm":false,"mt":false,"tr":false,"ac":false,"tp":false},{"t":50.655,"s":1,"f":7,"sus":0.0,"sl":-1,"slu":-1,"bn":0,"ho":false,"po":false,"hm":false,"hp":false,"pm":false,"mt":false,"tr":false,"ac":false,"tp":false},{"t":50.905,"s":1,"f":7,"sus":0.49,"sl":-1,"slu":-1,"bn":0,"ho":false,"po":false,"hm":false,"hp":false,"pm":false,"mt":false,"tr":false,"ac":false,"tp":false},{"t":51.398,"s":2,"f":9,"sus":0.0,"sl":-1,"slu":-1,"bn":0,"ho":false,"po":false,"hm":false,"hp":false,"pm":false,"mt":false,"tr":false,"ac":false,"tp":false},{"t":51.634,"s":1,"f":7,"sus":0.0,"sl":-1,"slu":-1,"bn":0,"ho":false,"po":false,"hm":false,"hp":false,"pm":false,"mt":false,"tr":false,"ac":false,"tp":false},{"t":51.87,"s":1,"f":7,"sus":0.0,"sl":-1,"slu":-1,"bn":0,"ho":false,"po":false,"hm":false,"hp":false,"pm":false,"mt":false,"tr":false,"ac":false,"tp":false},{"t":52.106,"s":0,"f":2,"sus":0.493,"sl":-1,"slu":-1,"bn":0,"ho":false,"po":false,"hm":false,"hp":false,"pm":false,"mt":false,"tr":false,"ac":false,"tp":false},{"t":52.854,"s":0,"f":2,"sus":0.0,"sl":-1,"slu":-1,"bn":0,"ho":false,"po":false,"hm":false,"hp":false,"pm":false,"mt":false,"tr":false,"ac":false,"tp":false},{"t":53.604,"s":0,"f":2,"sus":0.0,"sl":-1,"slu":-1,"bn":0,"ho":false,"po":false,"hm":false,"hp":false,"pm":false,"mt":false,"tr":false,"ac":false,"tp":false},{"t":53.86,"s":0,"f":2,"sus":0.0,"sl":-1,"slu":-1,"bn":0,"ho":false,"po":false,"hm":false,"hp":false,"pm":false,"mt":false,"tr":false,"ac":false,"tp":false},{"t":54.112,"s":0,"f":5,"sus":0.0,"sl":-1,"slu":-1,"bn":0,"ho":false,"po":false,"hm":false,"hp":false,"pm":false,"mt":false,"tr":false,"ac":false,"tp":false},{"t":54.365,"s":0,"f":5,"sus":0.0,"sl":-1,"slu":-1,"bn":0,"ho":false,"po":false,"hm":false,"hp":false,"pm":false,"mt":false,"tr":false,"ac":false,"tp":false},{"t":54.617,"s":0,"f":5,"sus":0.0,"sl":-1,"slu":-1,"bn":0,"ho":false,"po":false,"hm":false,"hp":false,"pm":false,"mt":false,"tr":false,"ac":false,"tp":false},{"t":54.865,"s":0,"f":5,"sus":0.0,"sl":-1,"slu":-1,"bn":0,"ho":false,"po":false,"hm":false,"hp":false,"pm":false,"mt":false,"tr":false,"ac":false,"tp":false},{"t":55.116,"s":0,"f":5,"sus":0.0,"sl":-1,"slu":-1,"bn":0,"ho":false,"po":false,"hm":false,"hp":false,"pm":false,"mt":false,"tr":false,"ac":false,"tp":false},{"t":55.367,"s":0,"f":5,"sus":0.0,"sl":-1,"slu":-1,"bn":0,"ho":false,"po":false,"hm":false,"hp":false,"pm":false,"mt":false,"tr":false,"ac":false,"tp":false},{"t":55.615,"s":0,"f":5,"sus":0.0,"sl":-1,"slu":-1,"bn":0,"ho":false,"po":false,"hm":false,"hp":false,"pm":false,"mt":false,"tr":false,"ac":false,"tp":false},{"t":55.864,"s":0,"f":0,"sus":0.0,"sl":-1,"slu":-1,"bn":0,"ho":false,"po":false,"hm":false,"hp":false,"pm":false,"mt":false,"tr":false,"ac":false,"tp":false},{"t":56.114,"s":0,"f":2,"sus":0.49,"sl":-1,"slu":-1,"bn":0,"ho":false,"po":false,"hm":false,"hp":false,"pm":false,"mt":false,"tr":false,"ac":false,"tp":false},{"t":56.856,"s":0,"f":2,"sus":0.0,"sl":-1,"slu":-1,"bn":0,"ho":false,"po":false,"hm":false,"hp":false,"pm":false,"mt":false,"tr":false,"ac":false,"tp":false},{"t":57.607,"s":0,"f":2,"sus":0.0,"sl":-1,"slu":-1,"bn":0,"ho":false,"po":false,"hm":false,"hp":false,"pm":false,"mt":false,"tr":false,"ac":false,"tp":false},{"t":57.856,"s":0,"f":2,"sus":0.0,"sl":-1,"slu":-1,"bn":0,"ho":false,"po":false,"hm":false,"hp":false,"pm":false,"mt":false,"tr":false,"ac":false,"tp":false},{"t":58.105,"s":0,"f":5,"sus":0.0,"sl":-1,"slu":-1,"bn":0,"ho":false,"po":false,"hm":false,"hp":false,"pm":false,"mt":false,"tr":false,"ac":false,"tp":false},{"t":58.356,"s":0,"f":5,"sus":0.002,"sl":-1,"slu":-1,"bn":0,"ho":false,"po":false,"hm":false,"hp":false,"pm":false,"mt":false,"tr":false,"ac":false,"tp":false},{"t":58.609,"s":0,"f":5,"sus":0.0,"sl":-1,"slu":-1,"bn":0,"ho":false,"po":false,"hm":false,"hp":false,"pm":false,"mt":false,"tr":false,"ac":false,"tp":false},{"t":58.863,"s":0,"f":5,"sus":0.0,"sl":-1,"slu":-1,"bn":0,"ho":false,"po":false,"hm":false,"hp":false,"pm":false,"mt":false,"tr":false,"ac":false,"tp":false},{"t":59.113,"s":0,"f":5,"sus":0.0,"sl":-1,"slu":-1,"bn":0,"ho":false,"po":false,"hm":false,"hp":false,"pm":false,"mt":false,"tr":false,"ac":false,"tp":false},{"t":59.616,"s":0,"f":5,"sus":0.0,"sl":-1,"slu":-1,"bn":0,"ho":false,"po":false,"hm":false,"hp":false,"pm":false,"mt":false,"tr":false,"ac":false,"tp":false},{"t":59.865,"s":0,"f":0,"sus":0.0,"sl":-1,"slu":-1,"bn":0,"ho":false,"po":false,"hm":false,"hp":false,"pm":false,"mt":false,"tr":false,"ac":false,"tp":false},{"t":60.114,"s":0,"f":2,"sus":0.501,"sl":-1,"slu":-1,"bn":0,"ho":false,"po":false,"hm":false,"hp":false,"pm":false,"mt":false,"tr":false,"ac":false,"tp":false},{"t":60.865,"s":0,"f":2,"sus":0.0,"sl":-1,"slu":-1,"bn":0,"ho":false,"po":false,"hm":false,"hp":false,"pm":false,"mt":false,"tr":false,"ac":false,"tp":false},{"t":61.619,"s":0,"f":2,"sus":0.0,"sl":-1,"slu":-1,"bn":0,"ho":false,"po":false,"hm":false,"hp":false,"pm":false,"mt":false,"tr":false,"ac":false,"tp":false},{"t":61.872,"s":0,"f":2,"sus":0.0,"sl":-1,"slu":-1,"bn":0,"ho":false,"po":false,"hm":false,"hp":false,"pm":false,"mt":false,"tr":false,"ac":false,"tp":false},{"t":62.119,"s":0,"f":5,"sus":0.0,"sl":-1,"slu":-1,"bn":0,"ho":false,"po":false,"hm":false,"hp":false,"pm":false,"mt":false,"tr":false,"ac":false,"tp":false},{"t":62.366,"s":0,"f":5,"sus":0.0,"sl":-1,"slu":-1,"bn":0,"ho":false,"po":false,"hm":false,"hp":false,"pm":false,"mt":false,"tr":false,"ac":false,"tp":false},{"t":62.61,"s":0,"f":5,"sus":0.002,"sl":-1,"slu":-1,"bn":0,"ho":false,"po":false,"hm":false,"hp":false,"pm":false,"mt":false,"tr":false,"ac":false,"tp":false},{"t":62.862,"s":0,"f":5,"sus":0.0,"sl":-1,"slu":-1,"bn":0,"ho":false,"po":false,"hm":false,"hp":false,"pm":false,"mt":false,"tr":false,"ac":false,"tp":false},{"t":63.111,"s":0,"f":5,"sus":0.0,"sl":-1,"slu":-1,"bn":0,"ho":false,"po":false,"hm":false,"hp":false,"pm":false,"mt":false,"tr":false,"ac":false,"tp":false},{"t":63.362,"s":0,"f":5,"sus":0.0,"sl":-1,"slu":-1,"bn":0,"ho":false,"po":false,"hm":false,"hp":false,"pm":false,"mt":false,"tr":false,"ac":false,"tp":false},{"t":63.612,"s":0,"f":5,"sus":0.0,"sl":-1,"slu":-1,"bn":0,"ho":false,"po":false,"hm":false,"hp":false,"pm":false,"mt":false,"tr":false,"ac":false,"tp":false},{"t":63.862,"s":0,"f":0,"sus":0.0,"sl":-1,"slu":-1,"bn":0,"ho":false,"po":false,"hm":false,"hp":false,"pm":false,"mt":false,"tr":false,"ac":false,"tp":false},{"t":64.113,"s":0,"f":2,"sus":0.492,"sl":-1,"slu":-1,"bn":0,"ho":false,"po":false,"hm":false,"hp":false,"pm":false,"mt":false,"tr":false,"ac":false,"tp":false},{"t":64.86,"s":0,"f":2,"sus":0.0,"sl":-1,"slu":-1,"bn":0,"ho":false,"po":false,"hm":false,"hp":false,"pm":false,"mt":false,"tr":false,"ac":false,"tp":false},{"t":65.607,"s":0,"f":2,"sus":0.002,"sl":-1,"slu":-1,"bn":0,"ho":false,"po":false,"hm":false,"hp":false,"pm":false,"mt":false,"tr":false,"ac":false,"tp":false},{"t":65.86,"s":0,"f":2,"sus":0.0,"sl":-1,"slu":-1,"bn":0,"ho":false,"po":false,"hm":false,"hp":false,"pm":false,"mt":false,"tr":false,"ac":false,"tp":false},{"t":66.111,"s":0,"f":5,"sus":0.0,"sl":-1,"slu":-1,"bn":0,"ho":false,"po":false,"hm":false,"hp":false,"pm":false,"mt":false,"tr":false,"ac":false,"tp":false},{"t":66.363,"s":0,"f":5,"sus":0.0,"sl":-1,"slu":-1,"bn":0,"ho":false,"po":false,"hm":false,"hp":false,"pm":false,"mt":false,"tr":false,"ac":false,"tp":false},{"t":66.612,"s":0,"f":5,"sus":0.0,"sl":-1,"slu":-1,"bn":0,"ho":false,"po":false,"hm":false,"hp":false,"pm":false,"mt":false,"tr":false,"ac":false,"tp":false},{"t":66.859,"s":0,"f":5,"sus":0.0,"sl":-1,"slu":-1,"bn":0,"ho":false,"po":false,"hm":false,"hp":false,"pm":false,"mt":false,"tr":false,"ac":false,"tp":false},{"t":67.107,"s":0,"f":5,"sus":0.0,"sl":-1,"slu":-1,"bn":0,"ho":false,"po":false,"hm":false,"hp":false,"pm":false,"mt":false,"tr":false,"ac":false,"tp":false},{"t":67.601,"s":1,"f":7,"sus":0.0,"sl":-1,"slu":-1,"bn":0,"ho":false,"po":false,"hm":false,"hp":false,"pm":false,"mt":false,"tr":false,"ac":false,"tp":false},{"t":67.847,"s":1,"f":8,"sus":0.0,"sl":-1,"slu":-1,"bn":0,"ho":false,"po":false,"hm":false,"hp":false,"pm":false,"mt":false,"tr":false,"ac":false,"tp":false},{"t":68.093,"s":1,"f":9,"sus":0.531,"sl":-1,"slu":-1,"bn":0,"ho":false,"po":false,"hm":false,"hp":false,"pm":false,"mt":false,"tr":false,"ac":false,"tp":false},{"t":68.627,"s":2,"f":7,"sus":0.0,"sl":-1,"slu":-1,"bn":0,"ho":false,"po":false,"hm":false,"hp":false,"pm":false,"mt":false,"tr":false,"ac":false,"tp":false},{"t":68.879,"s":1,"f":9,"sus":0.0,"sl":-1,"slu":-1,"bn":0,"ho":false,"po":false,"hm":false,"hp":false,"pm":false,"mt":false,"tr":false,"ac":false,"tp":false},{"t":69.109,"s":2,"f":7,"sus":0.0,"sl":-1,"slu":-1,"bn":0,"ho":false,"po":false,"hm":false,"hp":false,"pm":false,"mt":false,"tr":false,"ac":false,"tp":false},{"t":69.359,"s":1,"f":9,"sus":0.0,"sl":-1,"slu":-1,"bn":0,"ho":false,"po":false,"hm":false,"hp":false,"pm":false,"mt":false,"tr":false,"ac":false,"tp":false},{"t":69.629,"s":1,"f":9,"sus":0.0,"sl":-1,"slu":-1,"bn":0,"ho":false,"po":false,"hm":false,"hp":false,"pm":false,"mt":false,"tr":false,"ac":false,"tp":false},{"t":69.889,"s":1,"f":8,"sus":0.0,"sl":-1,"slu":-1,"bn":0,"ho":false,"po":false,"hm":false,"hp":false,"pm":false,"mt":false,"tr":false,"ac":false,"tp":false},{"t":70.139,"s":1,"f":7,"sus":0.0,"sl":-1,"slu":-1,"bn":0,"ho":false,"po":false,"hm":false,"hp":false,"pm":false,"mt":false,"tr":false,"ac":false,"tp":false},{"t":70.389,"s":2,"f":9,"sus":0.0,"sl":-1,"slu":-1,"bn":0,"ho":false,"po":false,"hm":false,"hp":false,"pm":false,"mt":false,"tr":false,"ac":false,"tp":false},{"t":70.639,"s":1,"f":7,"sus":0.0,"sl":-1,"slu":-1,"bn":0,"ho":false,"po":false,"hm":false,"hp":false,"pm":false,"mt":false,"tr":false,"ac":false,"tp":false},{"t":70.889,"s":1,"f":7,"sus":0.497,"sl":-1,"slu":-1,"bn":0,"ho":false,"po":false,"hm":false,"hp":false,"pm":false,"mt":false,"tr":false,"ac":false,"tp":false},{"t":71.389,"s":2,"f":9,"sus":0.0,"sl":-1,"slu":-1,"bn":0,"ho":false,"po":false,"hm":false,"hp":false,"pm":false,"mt":false,"tr":false,"ac":false,"tp":false},{"t":71.639,"s":1,"f":7,"sus":0.0,"sl":-1,"slu":-1,"bn":0,"ho":false,"po":false,"hm":false,"hp":false,"pm":false,"mt":false,"tr":false,"ac":false,"tp":false},{"t":71.889,"s":1,"f":8,"sus":0.0,"sl":-1,"slu":-1,"bn":0,"ho":false,"po":false,"hm":false,"hp":false,"pm":false,"mt":false,"tr":false,"ac":false,"tp":false},{"t":72.139,"s":1,"f":9,"sus":0.497,"sl":-1,"slu":-1,"bn":0,"ho":false,"po":false,"hm":false,"hp":false,"pm":false,"mt":false,"tr":false,"ac":false,"tp":false},{"t":72.639,"s":2,"f":7,"sus":0.0,"sl":-1,"slu":-1,"bn":0,"ho":false,"po":false,"hm":false,"hp":false,"pm":false,"mt":false,"tr":false,"ac":false,"tp":false},{"t":72.889,"s":1,"f":9,"sus":0.0,"sl":-1,"slu":-1,"bn":0,"ho":false,"po":false,"hm":false,"hp":false,"pm":false,"mt":false,"tr":false,"ac":false,"tp":false},{"t":73.139,"s":2,"f":7,"sus":0.0,"sl":-1,"slu":-1,"bn":0,"ho":false,"po":false,"hm":false,"hp":false,"pm":false,"mt":false,"tr":false,"ac":false,"tp":false},{"t":73.389,"s":1,"f":9,"sus":0.0,"sl":-1,"slu":-1,"bn":0,"ho":false,"po":false,"hm":false,"hp":false,"pm":false,"mt":false,"tr":false,"ac":false,"tp":false},{"t":73.639,"s":1,"f":9,"sus":0.0,"sl":-1,"slu":-1,"bn":0,"ho":false,"po":false,"hm":false,"hp":false,"pm":false,"mt":false,"tr":false,"ac":false,"tp":false},{"t":73.889,"s":1,"f":8,"sus":0.0,"sl":-1,"slu":-1,"bn":0,"ho":false,"po":false,"hm":false,"hp":false,"pm":false,"mt":false,"tr":false,"ac":false,"tp":false},{"t":74.139,"s":1,"f":7,"sus":0.0,"sl":-1,"slu":-1,"bn":0,"ho":false,"po":false,"hm":false,"hp":false,"pm":false,"mt":false,"tr":false,"ac":false,"tp":false},{"t":74.389,"s":2,"f":9,"sus":0.0,"sl":-1,"slu":-1,"bn":0,"ho":false,"po":false,"hm":false,"hp":false,"pm":false,"mt":false,"tr":false,"ac":false,"tp":false},{"t":74.639,"s":1,"f":7,"sus":0.0,"sl":-1,"slu":-1,"bn":0,"ho":false,"po":false,"hm":false,"hp":false,"pm":false,"mt":false,"tr":false,"ac":false,"tp":false},{"t":74.889,"s":1,"f":7,"sus":0.5,"sl":-1,"slu":-1,"bn":0,"ho":false,"po":false,"hm":false,"hp":false,"pm":false,"mt":false,"tr":false,"ac":false,"tp":false},{"t":75.392,"s":2,"f":9,"sus":0.0,"sl":-1,"slu":-1,"bn":0,"ho":false,"po":false,"hm":false,"hp":false,"pm":false,"mt":false,"tr":false,"ac":false,"tp":false},{"t":75.648,"s":1,"f":7,"sus":0.0,"sl":-1,"slu":-1,"bn":0,"ho":false,"po":false,"hm":false,"hp":false,"pm":false,"mt":false,"tr":false,"ac":false,"tp":false},{"t":75.904,"s":1,"f":8,"sus":0.0,"sl":-1,"slu":-1,"bn":0,"ho":false,"po":false,"hm":false,"hp":false,"pm":false,"mt":false,"tr":false,"ac":false,"tp":false},{"t":76.16,"s":1,"f":9,"sus":0.502,"sl":-1,"slu":-1,"bn":0,"ho":false,"po":false,"hm":false,"hp":false,"pm":false,"mt":false,"tr":false,"ac":false,"tp":false},{"t":76.665,"s":2,"f":7,"sus":0.0,"sl":-1,"slu":-1,"bn":0,"ho":false,"po":false,"hm":false,"hp":false,"pm":false,"mt":false,"tr":false,"ac":false,"tp":false},{"t":76.916,"s":1,"f":9,"sus":0.0,"sl":-1,"slu":-1,"bn":0,"ho":false,"po":false,"hm":false,"hp":false,"pm":false,"mt":false,"tr":false,"ac":false,"tp":false},{"t":77.167,"s":2,"f":7,"sus":0.0,"sl":-1,"slu":-1,"bn":0,"ho":false,"po":false,"hm":false,"hp":false,"pm":false,"mt":false,"tr":false,"ac":false,"tp":false},{"t":77.418,"s":1,"f":9,"sus":0.0,"sl":-1,"slu":-1,"bn":0,"ho":false,"po":false,"hm":false,"hp":false,"pm":false,"mt":false,"tr":false,"ac":false,"tp":false},{"t":77.669,"s":1,"f":9,"sus":0.0,"sl":-1,"slu":-1,"bn":0,"ho":false,"po":false,"hm":false,"hp":false,"pm":false,"mt":false,"tr":false,"ac":false,"tp":false},{"t":77.919,"s":1,"f":8,"sus":0.0,"sl":-1,"slu":-1,"bn":0,"ho":false,"po":false,"hm":false,"hp":false,"pm":false,"mt":false,"tr":false,"ac":false,"tp":false},{"t":78.17,"s":1,"f":7,"sus":0.0,"sl":-1,"slu":-1,"bn":0,"ho":false,"po":false,"hm":false,"hp":false,"pm":false,"mt":false,"tr":false,"ac":false,"tp":false},{"t":78.421,"s":2,"f":9,"sus":0.0,"sl":-1,"slu":-1,"bn":0,"ho":false,"po":false,"hm":false,"hp":false,"pm":false,"mt":false,"tr":false,"ac":false,"tp":false},{"t":78.672,"s":1,"f":7,"sus":0.0,"sl":-1,"slu":-1,"bn":0,"ho":false,"po":false,"hm":false,"hp":false,"pm":false,"mt":false,"tr":false,"ac":false,"tp":false},{"t":78.923,"s":1,"f":7,"sus":0.499,"sl":-1,"slu":-1,"bn":0,"ho":false,"po":false,"hm":false,"hp":false,"pm":false,"mt":false,"tr":false,"ac":false,"tp":false},{"t":79.425,"s":2,"f":9,"sus":0.0,"sl":-1,"slu":-1,"bn":0,"ho":false,"po":false,"hm":false,"hp":false,"pm":false,"mt":false,"tr":false,"ac":false,"tp":false},{"t":79.676,"s":1,"f":7,"sus":0.0,"sl":-1,"slu":-1,"bn":0,"ho":false,"po":false,"hm":false,"hp":false,"pm":false,"mt":false,"tr":false,"ac":false,"tp":false},{"t":79.927,"s":1,"f":8,"sus":0.0,"sl":-1,"slu":-1,"bn":0,"ho":false,"po":false,"hm":false,"hp":false,"pm":false,"mt":false,"tr":false,"ac":false,"tp":false},{"t":80.178,"s":1,"f":9,"sus":0.499,"sl":-1,"slu":-1,"bn":0,"ho":false,"po":false,"hm":false,"hp":false,"pm":false,"mt":false,"tr":false,"ac":false,"tp":false},{"t":80.68,"s":2,"f":7,"sus":0.0,"sl":-1,"slu":-1,"bn":0,"ho":false,"po":false,"hm":false,"hp":false,"pm":false,"mt":false,"tr":false,"ac":false,"tp":false},{"t":80.93,"s":1,"f":9,"sus":0.0,"sl":-1,"slu":-1,"bn":0,"ho":false,"po":false,"hm":false,"hp":false,"pm":false,"mt":false,"tr":false,"ac":false,"tp":false},{"t":81.181,"s":2,"f":7,"sus":0.0,"sl":-1,"slu":-1,"bn":0,"ho":false,"po":false,"hm":false,"hp":false,"pm":false,"mt":false,"tr":false,"ac":false,"tp":false},{"t":81.432,"s":1,"f":9,"sus":0.0,"sl":-1,"slu":-1,"bn":0,"ho":false,"po":false,"hm":false,"hp":false,"pm":false,"mt":false,"tr":false,"ac":false,"tp":false},{"t":81.683,"s":1,"f":9,"sus":0.0,"sl":-1,"slu":-1,"bn":0,"ho":false,"po":false,"hm":false,"hp":false,"pm":false,"mt":false,"tr":false,"ac":false,"tp":false},{"t":81.934,"s":1,"f":8,"sus":0.0,"sl":-1,"slu":-1,"bn":0,"ho":false,"po":false,"hm":false,"hp":false,"pm":false,"mt":false,"tr":false,"ac":false,"tp":false},{"t":82.185,"s":1,"f":7,"sus":0.0,"sl":-1,"slu":-1,"bn":0,"ho":false,"po":false,"hm":false,"hp":false,"pm":false,"mt":false,"tr":false,"ac":false,"tp":false},{"t":82.436,"s":2,"f":9,"sus":0.0,"sl":-1,"slu":-1,"bn":0,"ho":false,"po":false,"hm":false,"hp":false,"pm":false,"mt":false,"tr":false,"ac":false,"tp":false},{"t":82.686,"s":1,"f":7,"sus":0.0,"sl":-1,"slu":-1,"bn":0,"ho":false,"po":false,"hm":false,"hp":false,"pm":false,"mt":false,"tr":false,"ac":false,"tp":false},{"t":82.937,"s":1,"f":7,"sus":0.497,"sl":-1,"slu":-1,"bn":0,"ho":false,"po":false,"hm":false,"hp":false,"pm":false,"mt":false,"tr":false,"ac":false,"tp":false},{"t":83.437,"s":2,"f":9,"sus":0.0,"sl":-1,"slu":-1,"bn":0,"ho":false,"po":false,"hm":false,"hp":false,"pm":false,"mt":false,"tr":false,"ac":false,"tp":false},{"t":83.687,"s":1,"f":7,"sus":0.0,"sl":-1,"slu":-1,"bn":0,"ho":false,"po":false,"hm":false,"hp":false,"pm":false,"mt":false,"tr":false,"ac":false,"tp":false},{"t":83.937,"s":1,"f":7,"sus":0.0,"sl":-1,"slu":-1,"bn":0,"ho":false,"po":false,"hm":false,"hp":false,"pm":false,"mt":false,"tr":false,"ac":false,"tp":false},{"t":84.187,"s":0,"f":2,"sus":0.497,"sl":-1,"slu":-1,"bn":0,"ho":false,"po":false,"hm":false,"hp":false,"pm":false,"mt":false,"tr":false,"ac":false,"tp":false},{"t":84.937,"s":0,"f":2,"sus":0.0,"sl":-1,"slu":-1,"bn":0,"ho":false,"po":false,"hm":false,"hp":false,"pm":false,"mt":false,"tr":false,"ac":false,"tp":false},{"t":85.711,"s":0,"f":2,"sus":0.0,"sl":-1,"slu":-1,"bn":0,"ho":false,"po":false,"hm":false,"hp":false,"pm":false,"mt":false,"tr":false,"ac":false,"tp":false},{"t":85.969,"s":0,"f":2,"sus":0.0,"sl":-1,"slu":-1,"bn":0,"ho":false,"po":false,"hm":false,"hp":false,"pm":false,"mt":false,"tr":false,"ac":false,"tp":false},{"t":86.219,"s":0,"f":5,"sus":0.0,"sl":-1,"slu":-1,"bn":0,"ho":false,"po":false,"hm":false,"hp":false,"pm":false,"mt":false,"tr":false,"ac":false,"tp":false},{"t":86.469,"s":0,"f":5,"sus":0.0,"sl":-1,"slu":-1,"bn":0,"ho":false,"po":false,"hm":false,"hp":false,"pm":false,"mt":false,"tr":false,"ac":false,"tp":false},{"t":86.719,"s":0,"f":5,"sus":0.0,"sl":-1,"slu":-1,"bn":0,"ho":false,"po":false,"hm":false,"hp":false,"pm":false,"mt":false,"tr":false,"ac":false,"tp":false},{"t":86.969,"s":0,"f":5,"sus":0.0,"sl":-1,"slu":-1,"bn":0,"ho":false,"po":false,"hm":false,"hp":false,"pm":false,"mt":false,"tr":false,"ac":false,"tp":false},{"t":87.219,"s":0,"f":5,"sus":0.0,"sl":-1,"slu":-1,"bn":0,"ho":false,"po":false,"hm":false,"hp":false,"pm":false,"mt":false,"tr":false,"ac":false,"tp":false},{"t":87.469,"s":0,"f":5,"sus":0.0,"sl":-1,"slu":-1,"bn":0,"ho":false,"po":false,"hm":false,"hp":false,"pm":false,"mt":false,"tr":false,"ac":false,"tp":false},{"t":87.719,"s":0,"f":5,"sus":0.0,"sl":-1,"slu":-1,"bn":0,"ho":false,"po":false,"hm":false,"hp":false,"pm":false,"mt":false,"tr":false,"ac":false,"tp":false},{"t":87.969,"s":0,"f":0,"sus":0.0,"sl":-1,"slu":-1,"bn":0,"ho":false,"po":false,"hm":false,"hp":false,"pm":false,"mt":false,"tr":false,"ac":false,"tp":false},{"t":88.219,"s":0,"f":2,"sus":0.497,"sl":-1,"slu":-1,"bn":0,"ho":false,"po":false,"hm":false,"hp":false,"pm":false,"mt":false,"tr":false,"ac":false,"tp":false},{"t":88.969,"s":0,"f":2,"sus":0.0,"sl":-1,"slu":-1,"bn":0,"ho":false,"po":false,"hm":false,"hp":false,"pm":false,"mt":false,"tr":false,"ac":false,"tp":false},{"t":89.725,"s":0,"f":2,"sus":0.0,"sl":-1,"slu":-1,"bn":0,"ho":false,"po":false,"hm":false,"hp":false,"pm":false,"mt":false,"tr":false,"ac":false,"tp":false},{"t":89.977,"s":0,"f":2,"sus":0.0,"sl":-1,"slu":-1,"bn":0,"ho":false,"po":false,"hm":false,"hp":false,"pm":false,"mt":false,"tr":false,"ac":false,"tp":false},{"t":90.227,"s":0,"f":5,"sus":0.0,"sl":-1,"slu":-1,"bn":0,"ho":false,"po":false,"hm":false,"hp":false,"pm":false,"mt":false,"tr":false,"ac":false,"tp":false},{"t":90.481,"s":0,"f":5,"sus":0.0,"sl":-1,"slu":-1,"bn":0,"ho":false,"po":false,"hm":false,"hp":false,"pm":false,"mt":false,"tr":false,"ac":false,"tp":false},{"t":90.739,"s":0,"f":5,"sus":0.0,"sl":-1,"slu":-1,"bn":0,"ho":false,"po":false,"hm":false,"hp":false,"pm":false,"mt":false,"tr":false,"ac":false,"tp":false},{"t":90.993,"s":0,"f":5,"sus":0.0,"sl":-1,"slu":-1,"bn":0,"ho":false,"po":false,"hm":false,"hp":false,"pm":false,"mt":false,"tr":false,"ac":false,"tp":false},{"t":91.243,"s":0,"f":5,"sus":0.0,"sl":-1,"slu":-1,"bn":0,"ho":false,"po":false,"hm":false,"hp":false,"pm":false,"mt":false,"tr":false,"ac":false,"tp":false},{"t":91.75,"s":0,"f":5,"sus":0.0,"sl":-1,"slu":-1,"bn":0,"ho":false,"po":false,"hm":false,"hp":false,"pm":false,"mt":false,"tr":false,"ac":false,"tp":false},{"t":92.003,"s":0,"f":0,"sus":0.0,"sl":-1,"slu":-1,"bn":0,"ho":false,"po":false,"hm":false,"hp":false,"pm":false,"mt":false,"tr":false,"ac":false,"tp":false},{"t":92.257,"s":0,"f":2,"sus":0.506,"sl":-1,"slu":-1,"bn":0,"ho":false,"po":false,"hm":false,"hp":false,"pm":false,"mt":false,"tr":false,"ac":false,"tp":false},{"t":93.018,"s":0,"f":2,"sus":0.0,"sl":-1,"slu":-1,"bn":0,"ho":false,"po":false,"hm":false,"hp":false,"pm":false,"mt":false,"tr":false,"ac":false,"tp":false},{"t":93.774,"s":0,"f":2,"sus":0.0,"sl":-1,"slu":-1,"bn":0,"ho":false,"po":false,"hm":false,"hp":false,"pm":false,"mt":false,"tr":false,"ac":false,"tp":false},{"t":94.026,"s":0,"f":2,"sus":0.0,"sl":-1,"slu":-1,"bn":0,"ho":false,"po":false,"hm":false,"hp":false,"pm":false,"mt":false,"tr":false,"ac":false,"tp":false},{"t":94.278,"s":0,"f":5,"sus":0.0,"sl":-1,"slu":-1,"bn":0,"ho":false,"po":false,"hm":false,"hp":false,"pm":false,"mt":false,"tr":false,"ac":false,"tp":false},{"t":94.53,"s":0,"f":5,"sus":0.0,"sl":-1,"slu":-1,"bn":0,"ho":false,"po":false,"hm":false,"hp":false,"pm":false,"mt":false,"tr":false,"ac":false,"tp":false},{"t":94.782,"s":0,"f":5,"sus":0.0,"sl":-1,"slu":-1,"bn":0,"ho":false,"po":false,"hm":false,"hp":false,"pm":false,"mt":false,"tr":false,"ac":false,"tp":false},{"t":95.033,"s":0,"f":5,"sus":0.0,"sl":-1,"slu":-1,"bn":0,"ho":false,"po":false,"hm":false,"hp":false,"pm":false,"mt":false,"tr":false,"ac":false,"tp":false},{"t":95.283,"s":0,"f":5,"sus":0.0,"sl":-1,"slu":-1,"bn":0,"ho":false,"po":false,"hm":false,"hp":false,"pm":false,"mt":false,"tr":false,"ac":false,"tp":false},{"t":95.533,"s":0,"f":5,"sus":0.0,"sl":-1,"slu":-1,"bn":0,"ho":false,"po":false,"hm":false,"hp":false,"pm":false,"mt":false,"tr":false,"ac":false,"tp":false},{"t":95.783,"s":0,"f":5,"sus":0.0,"sl":-1,"slu":-1,"bn":0,"ho":false,"po":false,"hm":false,"hp":false,"pm":false,"mt":false,"tr":false,"ac":false,"tp":false},{"t":96.033,"s":0,"f":0,"sus":0.0,"sl":-1,"slu":-1,"bn":0,"ho":false,"po":false,"hm":false,"hp":false,"pm":false,"mt":false,"tr":false,"ac":false,"tp":false},{"t":96.283,"s":0,"f":2,"sus":0.497,"sl":-1,"slu":-1,"bn":0,"ho":false,"po":false,"hm":false,"hp":false,"pm":false,"mt":false,"tr":false,"ac":false,"tp":false},{"t":97.033,"s":0,"f":2,"sus":0.0,"sl":-1,"slu":-1,"bn":0,"ho":false,"po":false,"hm":false,"hp":false,"pm":false,"mt":false,"tr":false,"ac":false,"tp":false},{"t":97.783,"s":0,"f":2,"sus":0.0,"sl":-1,"slu":-1,"bn":0,"ho":false,"po":false,"hm":false,"hp":false,"pm":false,"mt":false,"tr":false,"ac":false,"tp":false},{"t":98.033,"s":0,"f":2,"sus":0.0,"sl":-1,"slu":-1,"bn":0,"ho":false,"po":false,"hm":false,"hp":false,"pm":false,"mt":false,"tr":false,"ac":false,"tp":false},{"t":98.283,"s":0,"f":5,"sus":0.0,"sl":-1,"slu":-1,"bn":0,"ho":false,"po":false,"hm":false,"hp":false,"pm":false,"mt":false,"tr":false,"ac":false,"tp":false},{"t":98.533,"s":0,"f":5,"sus":0.0,"sl":-1,"slu":-1,"bn":0,"ho":false,"po":false,"hm":false,"hp":false,"pm":false,"mt":false,"tr":false,"ac":false,"tp":false},{"t":98.783,"s":0,"f":5,"sus":0.0,"sl":-1,"slu":-1,"bn":0,"ho":false,"po":false,"hm":false,"hp":false,"pm":false,"mt":false,"tr":false,"ac":false,"tp":false},{"t":99.033,"s":0,"f":5,"sus":0.0,"sl":-1,"slu":-1,"bn":0,"ho":false,"po":false,"hm":false,"hp":false,"pm":false,"mt":false,"tr":false,"ac":false,"tp":false},{"t":99.283,"s":0,"f":5,"sus":0.0,"sl":-1,"slu":-1,"bn":0,"ho":false,"po":false,"hm":false,"hp":false,"pm":false,"mt":false,"tr":false,"ac":false,"tp":false},{"t":99.532,"s":0,"f":5,"sus":0.0,"sl":-1,"slu":-1,"bn":0,"ho":false,"po":false,"hm":false,"hp":false,"pm":false,"mt":false,"tr":false,"ac":false,"tp":false},{"t":99.78,"s":0,"f":5,"sus":0.0,"sl":-1,"slu":-1,"bn":0,"ho":false,"po":false,"hm":false,"hp":false,"pm":false,"mt":false,"tr":false,"ac":false,"tp":false},{"t":101.262,"s":1,"f":2,"sus":0.0,"sl":-1,"slu":-1,"bn":0,"ho":false,"po":false,"hm":false,"hp":false,"pm":false,"mt":false,"tr":false,"ac":false,"tp":false},{"t":101.507,"s":1,"f":2,"sus":0.0,"sl":-1,"slu":-1,"bn":0,"ho":false,"po":false,"hm":false,"hp":false,"pm":false,"mt":false,"tr":false,"ac":false,"tp":false},{"t":102.245,"s":1,"f":5,"sus":0.0,"sl":-1,"slu":-1,"bn":0,"ho":false,"po":false,"hm":false,"hp":false,"pm":false,"mt":false,"tr":false,"ac":false,"tp":false},{"t":102.737,"s":1,"f":5,"sus":0.0,"sl":-1,"slu":-1,"bn":0,"ho":false,"po":false,"hm":false,"hp":false,"pm":false,"mt":false,"tr":false,"ac":false,"tp":false},{"t":102.983,"s":1,"f":5,"sus":0.0,"sl":-1,"slu":-1,"bn":0,"ho":false,"po":false,"hm":false,"hp":false,"pm":false,"mt":false,"tr":false,"ac":false,"tp":false},{"t":103.476,"s":1,"f":5,"sus":0.0,"sl":-1,"slu":-1,"bn":0,"ho":false,"po":false,"hm":false,"hp":false,"pm":false,"mt":false,"tr":false,"ac":false,"tp":false},{"t":103.721,"s":1,"f":3,"sus":0.0,"sl":-1,"slu":-1,"bn":0,"ho":false,"po":false,"hm":false,"hp":false,"pm":false,"mt":false,"tr":false,"ac":false,"tp":false},{"t":104.213,"s":1,"f":2,"sus":0.0,"sl":-1,"slu":-1,"bn":0,"ho":false,"po":false,"hm":false,"hp":false,"pm":false,"mt":false,"tr":false,"ac":false,"tp":false},{"t":104.706,"s":1,"f":2,"sus":0.0,"sl":-1,"slu":-1,"bn":0,"ho":false,"po":false,"hm":false,"hp":false,"pm":false,"mt":false,"tr":false,"ac":false,"tp":false},{"t":104.951,"s":1,"f":2,"sus":0.0,"sl":-1,"slu":-1,"bn":0,"ho":false,"po":false,"hm":false,"hp":false,"pm":false,"mt":false,"tr":false,"ac":false,"tp":false},{"t":105.443,"s":1,"f":2,"sus":0.0,"sl":-1,"slu":-1,"bn":0,"ho":false,"po":false,"hm":false,"hp":false,"pm":false,"mt":false,"tr":false,"ac":false,"tp":false},{"t":105.69,"s":1,"f":2,"sus":0.0,"sl":-1,"slu":-1,"bn":0,"ho":false,"po":false,"hm":false,"hp":false,"pm":false,"mt":false,"tr":false,"ac":false,"tp":false},{"t":106.187,"s":1,"f":5,"sus":0.0,"sl":-1,"slu":-1,"bn":0,"ho":false,"po":false,"hm":false,"hp":false,"pm":false,"mt":false,"tr":false,"ac":false,"tp":false},{"t":106.687,"s":1,"f":5,"sus":0.0,"sl":-1,"slu":-1,"bn":0,"ho":false,"po":false,"hm":false,"hp":false,"pm":false,"mt":false,"tr":false,"ac":false,"tp":false},{"t":106.937,"s":1,"f":5,"sus":0.0,"sl":-1,"slu":-1,"bn":0,"ho":false,"po":false,"hm":false,"hp":false,"pm":false,"mt":false,"tr":false,"ac":false,"tp":false},{"t":107.437,"s":1,"f":5,"sus":0.0,"sl":-1,"slu":-1,"bn":0,"ho":false,"po":false,"hm":false,"hp":false,"pm":false,"mt":false,"tr":false,"ac":false,"tp":false},{"t":107.687,"s":1,"f":3,"sus":0.0,"sl":-1,"slu":-1,"bn":0,"ho":false,"po":false,"hm":false,"hp":false,"pm":false,"mt":false,"tr":false,"ac":false,"tp":false},{"t":107.937,"s":1,"f":0,"sus":0.0,"sl":-1,"slu":-1,"bn":0,"ho":false,"po":false,"hm":false,"hp":false,"pm":false,"mt":false,"tr":false,"ac":false,"tp":false},{"t":108.187,"s":1,"f":2,"sus":0.0,"sl":-1,"slu":-1,"bn":0,"ho":false,"po":false,"hm":false,"hp":false,"pm":false,"mt":false,"tr":false,"ac":false,"tp":false},{"t":108.687,"s":1,"f":2,"sus":0.0,"sl":-1,"slu":-1,"bn":0,"ho":false,"po":false,"hm":false,"hp":false,"pm":false,"mt":false,"tr":false,"ac":false,"tp":false},{"t":108.937,"s":1,"f":2,"sus":0.0,"sl":-1,"slu":-1,"bn":0,"ho":false,"po":false,"hm":false,"hp":false,"pm":false,"mt":false,"tr":false,"ac":false,"tp":false},{"t":109.437,"s":1,"f":2,"sus":0.0,"sl":-1,"slu":-1,"bn":0,"ho":false,"po":false,"hm":false,"hp":false,"pm":false,"mt":false,"tr":false,"ac":false,"tp":false},{"t":109.687,"s":1,"f":2,"sus":0.0,"sl":-1,"slu":-1,"bn":0,"ho":false,"po":false,"hm":false,"hp":false,"pm":false,"mt":false,"tr":false,"ac":false,"tp":false},{"t":109.937,"s":1,"f":4,"sus":0.0,"sl":-1,"slu":-1,"bn":0,"ho":false,"po":false,"hm":false,"hp":false,"pm":false,"mt":false,"tr":false,"ac":false,"tp":false},{"t":110.187,"s":1,"f":5,"sus":0.0,"sl":-1,"slu":-1,"bn":0,"ho":false,"po":false,"hm":false,"hp":false,"pm":false,"mt":false,"tr":false,"ac":false,"tp":false},{"t":110.687,"s":1,"f":5,"sus":0.0,"sl":-1,"slu":-1,"bn":0,"ho":false,"po":false,"hm":false,"hp":false,"pm":false,"mt":false,"tr":false,"ac":false,"tp":false},{"t":110.937,"s":1,"f":5,"sus":0.0,"sl":-1,"slu":-1,"bn":0,"ho":false,"po":false,"hm":false,"hp":false,"pm":false,"mt":false,"tr":false,"ac":false,"tp":false},{"t":111.411,"s":1,"f":5,"sus":0.004,"sl":-1,"slu":-1,"bn":0,"ho":false,"po":false,"hm":false,"hp":false,"pm":false,"mt":false,"tr":false,"ac":false,"tp":false},{"t":111.609,"s":1,"f":3,"sus":0.004,"sl":-1,"slu":-1,"bn":0,"ho":false,"po":false,"hm":false,"hp":false,"pm":false,"mt":false,"tr":false,"ac":false,"tp":false},{"t":111.833,"s":1,"f":0,"sus":0.0,"sl":-1,"slu":-1,"bn":0,"ho":false,"po":false,"hm":false,"hp":false,"pm":false,"mt":false,"tr":false,"ac":false,"tp":false},{"t":112.083,"s":1,"f":2,"sus":0.0,"sl":-1,"slu":-1,"bn":0,"ho":false,"po":false,"hm":false,"hp":false,"pm":false,"mt":false,"tr":false,"ac":false,"tp":false},{"t":112.583,"s":1,"f":2,"sus":0.0,"sl":-1,"slu":-1,"bn":0,"ho":false,"po":false,"hm":false,"hp":false,"pm":false,"mt":false,"tr":false,"ac":false,"tp":false},{"t":112.833,"s":1,"f":2,"sus":0.0,"sl":-1,"slu":-1,"bn":0,"ho":false,"po":false,"hm":false,"hp":false,"pm":false,"mt":false,"tr":false,"ac":false,"tp":false},{"t":113.333,"s":1,"f":2,"sus":0.0,"sl":-1,"slu":-1,"bn":0,"ho":false,"po":false,"hm":false,"hp":false,"pm":false,"mt":false,"tr":false,"ac":false,"tp":false},{"t":113.583,"s":1,"f":2,"sus":0.0,"sl":-1,"slu":-1,"bn":0,"ho":false,"po":false,"hm":false,"hp":false,"pm":false,"mt":false,"tr":false,"ac":false,"tp":false},{"t":113.833,"s":1,"f":4,"sus":0.0,"sl":-1,"slu":-1,"bn":0,"ho":false,"po":false,"hm":false,"hp":false,"pm":false,"mt":false,"tr":false,"ac":false,"tp":false},{"t":114.083,"s":1,"f":5,"sus":0.0,"sl":-1,"slu":-1,"bn":0,"ho":false,"po":false,"hm":false,"hp":false,"pm":false,"mt":false,"tr":false,"ac":false,"tp":false},{"t":114.333,"s":1,"f":5,"sus":0.0,"sl":-1,"slu":-1,"bn":0,"ho":false,"po":false,"hm":false,"hp":false,"pm":false,"mt":false,"tr":false,"ac":false,"tp":false},{"t":114.583,"s":1,"f":5,"sus":0.0,"sl":-1,"slu":-1,"bn":0,"ho":false,"po":false,"hm":false,"hp":false,"pm":false,"mt":false,"tr":false,"ac":false,"tp":false},{"t":114.821,"s":1,"f":5,"sus":0.0,"sl":-1,"slu":-1,"bn":0,"ho":false,"po":false,"hm":false,"hp":false,"pm":false,"mt":false,"tr":false,"ac":false,"tp":false},{"t":115.285,"s":1,"f":7,"sus":0.0,"sl":-1,"slu":-1,"bn":0,"ho":false,"po":false,"hm":false,"hp":false,"pm":false,"mt":false,"tr":false,"ac":false,"tp":false},{"t":115.535,"s":1,"f":7,"sus":0.0,"sl":-1,"slu":-1,"bn":0,"ho":false,"po":false,"hm":false,"hp":false,"pm":false,"mt":false,"tr":false,"ac":false,"tp":false},{"t":115.785,"s":1,"f":8,"sus":0.0,"sl":-1,"slu":-1,"bn":0,"ho":false,"po":false,"hm":false,"hp":false,"pm":false,"mt":false,"tr":false,"ac":false,"tp":false},{"t":116.035,"s":1,"f":9,"sus":0.497,"sl":-1,"slu":-1,"bn":0,"ho":false,"po":false,"hm":false,"hp":false,"pm":false,"mt":false,"tr":false,"ac":false,"tp":false},{"t":116.535,"s":2,"f":7,"sus":0.0,"sl":-1,"slu":-1,"bn":0,"ho":false,"po":false,"hm":false,"hp":false,"pm":false,"mt":false,"tr":false,"ac":false,"tp":false},{"t":116.785,"s":1,"f":9,"sus":0.0,"sl":-1,"slu":-1,"bn":0,"ho":false,"po":false,"hm":false,"hp":false,"pm":false,"mt":false,"tr":false,"ac":false,"tp":false},{"t":117.035,"s":2,"f":7,"sus":0.0,"sl":-1,"slu":-1,"bn":0,"ho":false,"po":false,"hm":false,"hp":false,"pm":false,"mt":false,"tr":false,"ac":false,"tp":false},{"t":117.285,"s":1,"f":9,"sus":0.0,"sl":-1,"slu":-1,"bn":0,"ho":false,"po":false,"hm":false,"hp":false,"pm":false,"mt":false,"tr":false,"ac":false,"tp":false},{"t":117.535,"s":1,"f":9,"sus":0.0,"sl":-1,"slu":-1,"bn":0,"ho":false,"po":false,"hm":false,"hp":false,"pm":false,"mt":false,"tr":false,"ac":false,"tp":false},{"t":117.785,"s":1,"f":8,"sus":0.0,"sl":-1,"slu":-1,"bn":0,"ho":false,"po":false,"hm":false,"hp":false,"pm":false,"mt":false,"tr":false,"ac":false,"tp":false},{"t":118.035,"s":1,"f":7,"sus":0.0,"sl":-1,"slu":-1,"bn":0,"ho":false,"po":false,"hm":false,"hp":false,"pm":false,"mt":false,"tr":false,"ac":false,"tp":false},{"t":118.279,"s":2,"f":9,"sus":0.0,"sl":-1,"slu":-1,"bn":0,"ho":false,"po":false,"hm":false,"hp":false,"pm":false,"mt":false,"tr":false,"ac":false,"tp":false},{"t":118.517,"s":1,"f":7,"sus":0.0,"sl":-1,"slu":-1,"bn":0,"ho":false,"po":false,"hm":false,"hp":false,"pm":false,"mt":false,"tr":false,"ac":false,"tp":false},{"t":118.761,"s":1,"f":7,"sus":0.497,"sl":-1,"slu":-1,"bn":0,"ho":false,"po":false,"hm":false,"hp":false,"pm":false,"mt":false,"tr":false,"ac":false,"tp":false},{"t":119.261,"s":2,"f":9,"sus":0.0,"sl":-1,"slu":-1,"bn":0,"ho":false,"po":false,"hm":false,"hp":false,"pm":false,"mt":false,"tr":false,"ac":false,"tp":false},{"t":119.511,"s":1,"f":7,"sus":0.0,"sl":-1,"slu":-1,"bn":0,"ho":false,"po":false,"hm":false,"hp":false,"pm":false,"mt":false,"tr":false,"ac":false,"tp":false},{"t":119.761,"s":1,"f":8,"sus":0.0,"sl":-1,"slu":-1,"bn":0,"ho":false,"po":false,"hm":false,"hp":false,"pm":false,"mt":false,"tr":false,"ac":false,"tp":false},{"t":120.011,"s":1,"f":9,"sus":0.497,"sl":-1,"slu":-1,"bn":0,"ho":false,"po":false,"hm":false,"hp":false,"pm":false,"mt":false,"tr":false,"ac":false,"tp":false},{"t":120.511,"s":2,"f":7,"sus":0.0,"sl":-1,"slu":-1,"bn":0,"ho":false,"po":false,"hm":false,"hp":false,"pm":false,"mt":false,"tr":false,"ac":false,"tp":false},{"t":120.743,"s":1,"f":9,"sus":0.003,"sl":-1,"slu":-1,"bn":0,"ho":false,"po":false,"hm":false,"hp":false,"pm":false,"mt":false,"tr":false,"ac":false,"tp":false},{"t":120.957,"s":2,"f":7,"sus":0.003,"sl":-1,"slu":-1,"bn":0,"ho":false,"po":false,"hm":false,"hp":false,"pm":false,"mt":false,"tr":false,"ac":false,"tp":false},{"t":121.189,"s":1,"f":9,"sus":0.0,"sl":-1,"slu":-1,"bn":0,"ho":false,"po":false,"hm":false,"hp":false,"pm":false,"mt":false,"tr":false,"ac":false,"tp":false},{"t":121.439,"s":1,"f":9,"sus":0.0,"sl":-1,"slu":-1,"bn":0,"ho":false,"po":false,"hm":false,"hp":false,"pm":false,"mt":false,"tr":false,"ac":false,"tp":false},{"t":121.689,"s":1,"f":8,"sus":0.0,"sl":-1,"slu":-1,"bn":0,"ho":false,"po":false,"hm":false,"hp":false,"pm":false,"mt":false,"tr":false,"ac":false,"tp":false},{"t":121.939,"s":1,"f":7,"sus":0.0,"sl":-1,"slu":-1,"bn":0,"ho":false,"po":false,"hm":false,"hp":false,"pm":false,"mt":false,"tr":false,"ac":false,"tp":false},{"t":122.189,"s":2,"f":9,"sus":0.0,"sl":-1,"slu":-1,"bn":0,"ho":false,"po":false,"hm":false,"hp":false,"pm":false,"mt":false,"tr":false,"ac":false,"tp":false},{"t":122.439,"s":1,"f":7,"sus":0.0,"sl":-1,"slu":-1,"bn":0,"ho":false,"po":false,"hm":false,"hp":false,"pm":false,"mt":false,"tr":false,"ac":false,"tp":false},{"t":122.689,"s":1,"f":7,"sus":0.497,"sl":-1,"slu":-1,"bn":0,"ho":false,"po":false,"hm":false,"hp":false,"pm":false,"mt":false,"tr":false,"ac":false,"tp":false},{"t":123.189,"s":2,"f":9,"sus":0.0,"sl":-1,"slu":-1,"bn":0,"ho":false,"po":false,"hm":false,"hp":false,"pm":false,"mt":false,"tr":false,"ac":false,"tp":false},{"t":123.939,"s":1,"f":9,"sus":0.497,"sl":-1,"slu":-1,"bn":0,"ho":false,"po":false,"hm":false,"hp":false,"pm":false,"mt":false,"tr":false,"ac":false,"tp":false},{"t":124.689,"s":1,"f":9,"sus":0.0,"sl":-1,"slu":-1,"bn":0,"ho":false,"po":false,"hm":false,"hp":false,"pm":false,"mt":false,"tr":false,"ac":false,"tp":false},{"t":125.189,"s":1,"f":9,"sus":0.0,"sl":-1,"slu":-1,"bn":0,"ho":false,"po":false,"hm":false,"hp":false,"pm":false,"mt":false,"tr":false,"ac":false,"tp":false},{"t":125.439,"s":1,"f":9,"sus":0.0,"sl":-1,"slu":-1,"bn":0,"ho":false,"po":false,"hm":false,"hp":false,"pm":false,"mt":false,"tr":false,"ac":false,"tp":false},{"t":125.939,"s":1,"f":7,"sus":0.0,"sl":-1,"slu":-1,"bn":0,"ho":false,"po":false,"hm":false,"hp":false,"pm":false,"mt":false,"tr":false,"ac":false,"tp":false},{"t":126.625,"s":1,"f":7,"sus":0.497,"sl":-1,"slu":-1,"bn":0,"ho":false,"po":false,"hm":false,"hp":false,"pm":false,"mt":false,"tr":false,"ac":false,"tp":false},{"t":127.125,"s":2,"f":9,"sus":0.0,"sl":-1,"slu":-1,"bn":0,"ho":false,"po":false,"hm":false,"hp":false,"pm":false,"mt":false,"tr":false,"ac":false,"tp":false},{"t":127.375,"s":1,"f":7,"sus":0.0,"sl":-1,"slu":-1,"bn":0,"ho":false,"po":false,"hm":false,"hp":false,"pm":false,"mt":false,"tr":false,"ac":false,"tp":false},{"t":127.875,"s":1,"f":9,"sus":0.497,"sl":-1,"slu":-1,"bn":0,"ho":false,"po":false,"hm":false,"hp":false,"pm":false,"mt":false,"tr":false,"ac":false,"tp":false},{"t":128.625,"s":1,"f":9,"sus":0.0,"sl":-1,"slu":-1,"bn":0,"ho":false,"po":false,"hm":false,"hp":false,"pm":false,"mt":false,"tr":false,"ac":false,"tp":false},{"t":129.113,"s":1,"f":9,"sus":0.0,"sl":-1,"slu":-1,"bn":0,"ho":false,"po":false,"hm":false,"hp":false,"pm":false,"mt":false,"tr":false,"ac":false,"tp":false},{"t":129.827,"s":1,"f":7,"sus":0.0,"sl":-1,"slu":-1,"bn":0,"ho":false,"po":false,"hm":false,"hp":false,"pm":false,"mt":false,"tr":false,"ac":false,"tp":false},{"t":130.577,"s":1,"f":7,"sus":0.487,"sl":-1,"slu":-1,"bn":0,"ho":false,"po":false,"hm":false,"hp":false,"pm":false,"mt":false,"tr":false,"ac":false,"tp":false},{"t":131.067,"s":2,"f":9,"sus":0.0,"sl":-1,"slu":-1,"bn":0,"ho":false,"po":false,"hm":false,"hp":false,"pm":false,"mt":false,"tr":false,"ac":false,"tp":false},{"t":131.297,"s":1,"f":7,"sus":0.0,"sl":-1,"slu":-1,"bn":0,"ho":false,"po":false,"hm":false,"hp":false,"pm":false,"mt":false,"tr":false,"ac":false,"tp":false},{"t":131.778,"s":1,"f":9,"sus":0.483,"sl":-1,"slu":-1,"bn":0,"ho":false,"po":false,"hm":false,"hp":false,"pm":false,"mt":false,"tr":false,"ac":false,"tp":false},{"t":132.507,"s":1,"f":9,"sus":0.0,"sl":-1,"slu":-1,"bn":0,"ho":false,"po":false,"hm":false,"hp":false,"pm":false,"mt":false,"tr":false,"ac":false,"tp":false},{"t":132.996,"s":1,"f":9,"sus":0.0,"sl":-1,"slu":-1,"bn":0,"ho":false,"po":false,"hm":false,"hp":false,"pm":false,"mt":false,"tr":false,"ac":false,"tp":false},{"t":133.242,"s":1,"f":9,"sus":0.0,"sl":-1,"slu":-1,"bn":0,"ho":false,"po":false,"hm":false,"hp":false,"pm":false,"mt":false,"tr":false,"ac":false,"tp":false},{"t":133.734,"s":1,"f":7,"sus":0.0,"sl":-1,"slu":-1,"bn":0,"ho":false,"po":false,"hm":false,"hp":false,"pm":false,"mt":false,"tr":false,"ac":false,"tp":false},{"t":134.472,"s":1,"f":7,"sus":0.488,"sl":-1,"slu":-1,"bn":0,"ho":false,"po":false,"hm":false,"hp":false,"pm":false,"mt":false,"tr":false,"ac":false,"tp":false},{"t":134.963,"s":2,"f":9,"sus":0.0,"sl":-1,"slu":-1,"bn":0,"ho":false,"po":false,"hm":false,"hp":false,"pm":false,"mt":false,"tr":false,"ac":false,"tp":false},{"t":135.208,"s":1,"f":7,"sus":0.0,"sl":-1,"slu":-1,"bn":0,"ho":false,"po":false,"hm":false,"hp":false,"pm":false,"mt":false,"tr":false,"ac":false,"tp":false},{"t":135.698,"s":1,"f":9,"sus":0.487,"sl":-1,"slu":-1,"bn":0,"ho":false,"po":false,"hm":false,"hp":false,"pm":false,"mt":false,"tr":false,"ac":false,"tp":false},{"t":136.433,"s":1,"f":9,"sus":0.0,"sl":-1,"slu":-1,"bn":0,"ho":false,"po":false,"hm":false,"hp":false,"pm":false,"mt":false,"tr":false,"ac":false,"tp":false},{"t":136.922,"s":1,"f":9,"sus":0.0,"sl":-1,"slu":-1,"bn":0,"ho":false,"po":false,"hm":false,"hp":false,"pm":false,"mt":false,"tr":false,"ac":false,"tp":false},{"t":138.38,"s":1,"f":7,"sus":0.484,"sl":-1,"slu":-1,"bn":0,"ho":false,"po":false,"hm":false,"hp":false,"pm":false,"mt":false,"tr":false,"ac":false,"tp":false},{"t":138.867,"s":2,"f":9,"sus":0.0,"sl":-1,"slu":-1,"bn":0,"ho":false,"po":false,"hm":false,"hp":false,"pm":false,"mt":false,"tr":false,"ac":false,"tp":false},{"t":139.112,"s":1,"f":7,"sus":0.0,"sl":-1,"slu":-1,"bn":0,"ho":false,"po":false,"hm":false,"hp":false,"pm":false,"mt":false,"tr":false,"ac":false,"tp":false},{"t":139.602,"s":1,"f":9,"sus":0.487,"sl":-1,"slu":-1,"bn":0,"ho":false,"po":false,"hm":false,"hp":false,"pm":false,"mt":false,"tr":false,"ac":false,"tp":false},{"t":140.337,"s":1,"f":9,"sus":0.0,"sl":-1,"slu":-1,"bn":0,"ho":false,"po":false,"hm":false,"hp":false,"pm":false,"mt":false,"tr":false,"ac":false,"tp":false},{"t":140.828,"s":1,"f":9,"sus":0.0,"sl":-1,"slu":-1,"bn":0,"ho":false,"po":false,"hm":false,"hp":false,"pm":false,"mt":false,"tr":false,"ac":false,"tp":false},{"t":141.073,"s":1,"f":9,"sus":0.0,"sl":-1,"slu":-1,"bn":0,"ho":false,"po":false,"hm":false,"hp":false,"pm":false,"mt":false,"tr":false,"ac":false,"tp":false},{"t":141.563,"s":1,"f":7,"sus":0.0,"sl":-1,"slu":-1,"bn":0,"ho":false,"po":false,"hm":false,"hp":false,"pm":false,"mt":false,"tr":false,"ac":false,"tp":false},{"t":142.298,"s":1,"f":7,"sus":0.487,"sl":-1,"slu":-1,"bn":0,"ho":false,"po":false,"hm":false,"hp":false,"pm":false,"mt":false,"tr":false,"ac":false,"tp":false},{"t":142.788,"s":2,"f":9,"sus":0.0,"sl":-1,"slu":-1,"bn":0,"ho":false,"po":false,"hm":false,"hp":false,"pm":false,"mt":false,"tr":false,"ac":false,"tp":false},{"t":143.032,"s":1,"f":7,"sus":0.0,"sl":-1,"slu":-1,"bn":0,"ho":false,"po":false,"hm":false,"hp":false,"pm":false,"mt":false,"tr":false,"ac":false,"tp":false},{"t":143.531,"s":1,"f":9,"sus":0.497,"sl":-1,"slu":-1,"bn":0,"ho":false,"po":false,"hm":false,"hp":false,"pm":false,"mt":false,"tr":false,"ac":false,"tp":false},{"t":144.281,"s":1,"f":9,"sus":0.0,"sl":-1,"slu":-1,"bn":0,"ho":false,"po":false,"hm":false,"hp":false,"pm":false,"mt":false,"tr":false,"ac":false,"tp":false},{"t":144.773,"s":1,"f":9,"sus":0.0,"sl":-1,"slu":-1,"bn":0,"ho":false,"po":false,"hm":false,"hp":false,"pm":false,"mt":false,"tr":false,"ac":false,"tp":false},{"t":145.499,"s":1,"f":7,"sus":0.0,"sl":-1,"slu":-1,"bn":0,"ho":false,"po":false,"hm":false,"hp":false,"pm":false,"mt":false,"tr":false,"ac":false,"tp":false},{"t":146.249,"s":1,"f":7,"sus":0.485,"sl":-1,"slu":-1,"bn":0,"ho":false,"po":false,"hm":false,"hp":false,"pm":false,"mt":false,"tr":false,"ac":false,"tp":false},{"t":146.737,"s":2,"f":9,"sus":0.0,"sl":-1,"slu":-1,"bn":0,"ho":false,"po":false,"hm":false,"hp":false,"pm":false,"mt":false,"tr":false,"ac":false,"tp":false},{"t":146.963,"s":1,"f":7,"sus":0.0,"sl":-1,"slu":-1,"bn":0,"ho":false,"po":false,"hm":false,"hp":false,"pm":false,"mt":false,"tr":false,"ac":false,"tp":false},{"t":147.44,"s":1,"f":9,"sus":0.48,"sl":-1,"slu":-1,"bn":0,"ho":false,"po":false,"hm":false,"hp":false,"pm":false,"mt":false,"tr":false,"ac":false,"tp":false},{"t":148.165,"s":1,"f":9,"sus":0.0,"sl":-1,"slu":-1,"bn":0,"ho":false,"po":false,"hm":false,"hp":false,"pm":false,"mt":false,"tr":false,"ac":false,"tp":false},{"t":148.65,"s":1,"f":9,"sus":0.0,"sl":-1,"slu":-1,"bn":0,"ho":false,"po":false,"hm":false,"hp":false,"pm":false,"mt":false,"tr":false,"ac":false,"tp":false},{"t":148.894,"s":1,"f":9,"sus":0.0,"sl":-1,"slu":-1,"bn":0,"ho":false,"po":false,"hm":false,"hp":false,"pm":false,"mt":false,"tr":false,"ac":false,"tp":false},{"t":150.114,"s":1,"f":7,"sus":0.486,"sl":-1,"slu":-1,"bn":0,"ho":false,"po":false,"hm":false,"hp":false,"pm":false,"mt":false,"tr":false,"ac":false,"tp":false},{"t":150.603,"s":2,"f":9,"sus":0.0,"sl":-1,"slu":-1,"bn":0,"ho":false,"po":false,"hm":false,"hp":false,"pm":false,"mt":false,"tr":false,"ac":false,"tp":false},{"t":150.847,"s":1,"f":7,"sus":0.0,"sl":-1,"slu":-1,"bn":0,"ho":false,"po":false,"hm":false,"hp":false,"pm":false,"mt":false,"tr":false,"ac":false,"tp":false},{"t":152.067,"s":1,"f":9,"sus":0.0,"sl":-1,"slu":-1,"bn":0,"ho":false,"po":false,"hm":false,"hp":false,"pm":false,"mt":false,"tr":false,"ac":false,"tp":false},{"t":152.554,"s":1,"f":9,"sus":0.0,"sl":-1,"slu":-1,"bn":0,"ho":false,"po":false,"hm":false,"hp":false,"pm":false,"mt":false,"tr":false,"ac":false,"tp":false},{"t":154.018,"s":1,"f":7,"sus":0.488,"sl":-1,"slu":-1,"bn":0,"ho":false,"po":false,"hm":false,"hp":false,"pm":false,"mt":false,"tr":false,"ac":false,"tp":false},{"t":154.509,"s":2,"f":9,"sus":0.0,"sl":-1,"slu":-1,"bn":0,"ho":false,"po":false,"hm":false,"hp":false,"pm":false,"mt":false,"tr":false,"ac":false,"tp":false},{"t":154.759,"s":1,"f":7,"sus":0.0,"sl":-1,"slu":-1,"bn":0,"ho":false,"po":false,"hm":false,"hp":false,"pm":false,"mt":false,"tr":false,"ac":false,"tp":false},{"t":155.259,"s":0,"f":2,"sus":0.497,"sl":-1,"slu":-1,"bn":0,"ho":false,"po":false,"hm":false,"hp":false,"pm":false,"mt":false,"tr":false,"ac":false,"tp":false},{"t":156.009,"s":0,"f":2,"sus":0.0,"sl":-1,"slu":-1,"bn":0,"ho":false,"po":false,"hm":false,"hp":false,"pm":false,"mt":false,"tr":false,"ac":false,"tp":false},{"t":156.729,"s":0,"f":2,"sus":0.0,"sl":-1,"slu":-1,"bn":0,"ho":false,"po":false,"hm":false,"hp":false,"pm":false,"mt":false,"tr":false,"ac":false,"tp":false},{"t":156.97,"s":0,"f":2,"sus":0.0,"sl":-1,"slu":-1,"bn":0,"ho":false,"po":false,"hm":false,"hp":false,"pm":false,"mt":false,"tr":false,"ac":false,"tp":false},{"t":157.221,"s":0,"f":5,"sus":0.0,"sl":-1,"slu":-1,"bn":0,"ho":false,"po":false,"hm":false,"hp":false,"pm":false,"mt":false,"tr":false,"ac":false,"tp":false},{"t":157.471,"s":0,"f":5,"sus":0.0,"sl":-1,"slu":-1,"bn":0,"ho":false,"po":false,"hm":false,"hp":false,"pm":false,"mt":false,"tr":false,"ac":false,"tp":false},{"t":157.722,"s":0,"f":5,"sus":0.0,"sl":-1,"slu":-1,"bn":0,"ho":false,"po":false,"hm":false,"hp":false,"pm":false,"mt":false,"tr":false,"ac":false,"tp":false},{"t":157.973,"s":0,"f":5,"sus":0.0,"sl":-1,"slu":-1,"bn":0,"ho":false,"po":false,"hm":false,"hp":false,"pm":false,"mt":false,"tr":false,"ac":false,"tp":false},{"t":158.224,"s":0,"f":5,"sus":0.0,"sl":-1,"slu":-1,"bn":0,"ho":false,"po":false,"hm":false,"hp":false,"pm":false,"mt":false,"tr":false,"ac":false,"tp":false},{"t":158.475,"s":0,"f":5,"sus":0.0,"sl":-1,"slu":-1,"bn":0,"ho":false,"po":false,"hm":false,"hp":false,"pm":false,"mt":false,"tr":false,"ac":false,"tp":false},{"t":158.726,"s":0,"f":5,"sus":0.0,"sl":-1,"slu":-1,"bn":0,"ho":false,"po":false,"hm":false,"hp":false,"pm":false,"mt":false,"tr":false,"ac":false,"tp":false},{"t":158.976,"s":0,"f":0,"sus":0.0,"sl":-1,"slu":-1,"bn":0,"ho":false,"po":false,"hm":false,"hp":false,"pm":false,"mt":false,"tr":false,"ac":false,"tp":false},{"t":159.227,"s":0,"f":2,"sus":0.498,"sl":-1,"slu":-1,"bn":0,"ho":false,"po":false,"hm":false,"hp":false,"pm":false,"mt":false,"tr":false,"ac":false,"tp":false},{"t":159.98,"s":0,"f":2,"sus":0.0,"sl":-1,"slu":-1,"bn":0,"ho":false,"po":false,"hm":false,"hp":false,"pm":false,"mt":false,"tr":false,"ac":false,"tp":false},{"t":160.732,"s":0,"f":2,"sus":0.0,"sl":-1,"slu":-1,"bn":0,"ho":false,"po":false,"hm":false,"hp":false,"pm":false,"mt":false,"tr":false,"ac":false,"tp":false},{"t":160.983,"s":0,"f":2,"sus":0.0,"sl":-1,"slu":-1,"bn":0,"ho":false,"po":false,"hm":false,"hp":false,"pm":false,"mt":false,"tr":false,"ac":false,"tp":false},{"t":161.234,"s":0,"f":5,"sus":0.0,"sl":-1,"slu":-1,"bn":0,"ho":false,"po":false,"hm":false,"hp":false,"pm":false,"mt":false,"tr":false,"ac":false,"tp":false},{"t":161.485,"s":0,"f":5,"sus":0.0,"sl":-1,"slu":-1,"bn":0,"ho":false,"po":false,"hm":false,"hp":false,"pm":false,"mt":false,"tr":false,"ac":false,"tp":false},{"t":161.736,"s":0,"f":5,"sus":0.0,"sl":-1,"slu":-1,"bn":0,"ho":false,"po":false,"hm":false,"hp":false,"pm":false,"mt":false,"tr":false,"ac":false,"tp":false},{"t":161.986,"s":0,"f":5,"sus":0.0,"sl":-1,"slu":-1,"bn":0,"ho":false,"po":false,"hm":false,"hp":false,"pm":false,"mt":false,"tr":false,"ac":false,"tp":false},{"t":162.237,"s":0,"f":5,"sus":0.0,"sl":-1,"slu":-1,"bn":0,"ho":false,"po":false,"hm":false,"hp":false,"pm":false,"mt":false,"tr":false,"ac":false,"tp":false},{"t":162.739,"s":0,"f":5,"sus":0.0,"sl":-1,"slu":-1,"bn":0,"ho":false,"po":false,"hm":false,"hp":false,"pm":false,"mt":false,"tr":false,"ac":false,"tp":false},{"t":162.99,"s":0,"f":0,"sus":0.0,"sl":-1,"slu":-1,"bn":0,"ho":false,"po":false,"hm":false,"hp":false,"pm":false,"mt":false,"tr":false,"ac":false,"tp":false},{"t":163.241,"s":0,"f":2,"sus":0.462,"sl":-1,"slu":-1,"bn":0,"ho":false,"po":false,"hm":false,"hp":false,"pm":false,"mt":false,"tr":false,"ac":false,"tp":false},{"t":163.946,"s":0,"f":2,"sus":0.0,"sl":-1,"slu":-1,"bn":0,"ho":false,"po":false,"hm":false,"hp":false,"pm":false,"mt":false,"tr":false,"ac":false,"tp":false},{"t":164.707,"s":0,"f":2,"sus":0.0,"sl":-1,"slu":-1,"bn":0,"ho":false,"po":false,"hm":false,"hp":false,"pm":false,"mt":false,"tr":false,"ac":false,"tp":false},{"t":164.959,"s":0,"f":2,"sus":0.002,"sl":-1,"slu":-1,"bn":0,"ho":false,"po":false,"hm":false,"hp":false,"pm":false,"mt":false,"tr":false,"ac":false,"tp":false},{"t":165.212,"s":0,"f":5,"sus":0.002,"sl":-1,"slu":-1,"bn":0,"ho":false,"po":false,"hm":false,"hp":false,"pm":false,"mt":false,"tr":false,"ac":false,"tp":false},{"t":165.466,"s":0,"f":5,"sus":0.0,"sl":-1,"slu":-1,"bn":0,"ho":false,"po":false,"hm":false,"hp":false,"pm":false,"mt":false,"tr":false,"ac":false,"tp":false},{"t":165.72,"s":0,"f":5,"sus":0.0,"sl":-1,"slu":-1,"bn":0,"ho":false,"po":false,"hm":false,"hp":false,"pm":false,"mt":false,"tr":false,"ac":false,"tp":false},{"t":165.974,"s":0,"f":5,"sus":0.0,"sl":-1,"slu":-1,"bn":0,"ho":false,"po":false,"hm":false,"hp":false,"pm":false,"mt":false,"tr":false,"ac":false,"tp":false},{"t":166.227,"s":0,"f":5,"sus":0.0,"sl":-1,"slu":-1,"bn":0,"ho":false,"po":false,"hm":false,"hp":false,"pm":false,"mt":false,"tr":false,"ac":false,"tp":false},{"t":166.474,"s":0,"f":5,"sus":0.0,"sl":-1,"slu":-1,"bn":0,"ho":false,"po":false,"hm":false,"hp":false,"pm":false,"mt":false,"tr":false,"ac":false,"tp":false},{"t":166.719,"s":0,"f":5,"sus":0.0,"sl":-1,"slu":-1,"bn":0,"ho":false,"po":false,"hm":false,"hp":false,"pm":false,"mt":false,"tr":false,"ac":false,"tp":false},{"t":166.97,"s":0,"f":0,"sus":0.0,"sl":-1,"slu":-1,"bn":0,"ho":false,"po":false,"hm":false,"hp":false,"pm":false,"mt":false,"tr":false,"ac":false,"tp":false},{"t":167.225,"s":0,"f":2,"sus":0.475,"sl":-1,"slu":-1,"bn":0,"ho":false,"po":false,"hm":false,"hp":false,"pm":false,"mt":false,"tr":false,"ac":false,"tp":false},{"t":167.955,"s":0,"f":2,"sus":0.002,"sl":-1,"slu":-1,"bn":0,"ho":false,"po":false,"hm":false,"hp":false,"pm":false,"mt":false,"tr":false,"ac":false,"tp":false},{"t":168.704,"s":0,"f":2,"sus":0.0,"sl":-1,"slu":-1,"bn":0,"ho":false,"po":false,"hm":false,"hp":false,"pm":false,"mt":false,"tr":false,"ac":false,"tp":false},{"t":168.941,"s":0,"f":2,"sus":0.0,"sl":-1,"slu":-1,"bn":0,"ho":false,"po":false,"hm":false,"hp":false,"pm":false,"mt":false,"tr":false,"ac":false,"tp":false},{"t":169.183,"s":0,"f":5,"sus":0.0,"sl":-1,"slu":-1,"bn":0,"ho":false,"po":false,"hm":false,"hp":false,"pm":false,"mt":false,"tr":false,"ac":false,"tp":false},{"t":169.429,"s":0,"f":5,"sus":0.0,"sl":-1,"slu":-1,"bn":0,"ho":false,"po":false,"hm":false,"hp":false,"pm":false,"mt":false,"tr":false,"ac":false,"tp":false},{"t":169.679,"s":0,"f":5,"sus":0.0,"sl":-1,"slu":-1,"bn":0,"ho":false,"po":false,"hm":false,"hp":false,"pm":false,"mt":false,"tr":false,"ac":false,"tp":false},{"t":169.929,"s":0,"f":5,"sus":0.0,"sl":-1,"slu":-1,"bn":0,"ho":false,"po":false,"hm":false,"hp":false,"pm":false,"mt":false,"tr":false,"ac":false,"tp":false},{"t":170.179,"s":0,"f":5,"sus":0.0,"sl":-1,"slu":-1,"bn":0,"ho":false,"po":false,"hm":false,"hp":false,"pm":false,"mt":false,"tr":false,"ac":false,"tp":false},{"t":170.433,"s":0,"f":5,"sus":0.0,"sl":-1,"slu":-1,"bn":0,"ho":false,"po":false,"hm":false,"hp":false,"pm":false,"mt":false,"tr":false,"ac":false,"tp":false},{"t":170.691,"s":0,"f":5,"sus":0.0,"sl":-1,"slu":-1,"bn":0,"ho":false,"po":false,"hm":false,"hp":false,"pm":false,"mt":false,"tr":false,"ac":false,"tp":false},{"t":171.193,"s":1,"f":2,"sus":0.0,"sl":-1,"slu":-1,"bn":0,"ho":false,"po":false,"hm":false,"hp":false,"pm":false,"mt":false,"tr":false,"ac":false,"tp":false},{"t":172.188,"s":1,"f":2,"sus":0.0,"sl":-1,"slu":-1,"bn":0,"ho":false,"po":false,"hm":false,"hp":false,"pm":false,"mt":false,"tr":false,"ac":false,"tp":false},{"t":172.437,"s":1,"f":2,"sus":0.0,"sl":-1,"slu":-1,"bn":0,"ho":false,"po":false,"hm":false,"hp":false,"pm":false,"mt":false,"tr":false,"ac":false,"tp":false},{"t":173.185,"s":1,"f":5,"sus":0.0,"sl":-1,"slu":-1,"bn":0,"ho":false,"po":false,"hm":false,"hp":false,"pm":false,"mt":false,"tr":false,"ac":false,"tp":false},{"t":173.682,"s":1,"f":5,"sus":0.0,"sl":-1,"slu":-1,"bn":0,"ho":false,"po":false,"hm":false,"hp":false,"pm":false,"mt":false,"tr":false,"ac":false,"tp":false},{"t":173.93,"s":1,"f":5,"sus":0.0,"sl":-1,"slu":-1,"bn":0,"ho":false,"po":false,"hm":false,"hp":false,"pm":false,"mt":false,"tr":false,"ac":false,"tp":false},{"t":174.415,"s":1,"f":5,"sus":0.0,"sl":-1,"slu":-1,"bn":0,"ho":false,"po":false,"hm":false,"hp":false,"pm":false,"mt":false,"tr":false,"ac":false,"tp":false},{"t":174.637,"s":1,"f":3,"sus":0.0,"sl":-1,"slu":-1,"bn":0,"ho":false,"po":false,"hm":false,"hp":false,"pm":false,"mt":false,"tr":false,"ac":false,"tp":false},{"t":175.116,"s":1,"f":2,"sus":0.0,"sl":-1,"slu":-1,"bn":0,"ho":false,"po":false,"hm":false,"hp":false,"pm":false,"mt":false,"tr":false,"ac":false,"tp":false},{"t":175.606,"s":1,"f":2,"sus":0.0,"sl":-1,"slu":-1,"bn":0,"ho":false,"po":false,"hm":false,"hp":false,"pm":false,"mt":false,"tr":false,"ac":false,"tp":false},{"t":175.852,"s":1,"f":2,"sus":0.0,"sl":-1,"slu":-1,"bn":0,"ho":false,"po":false,"hm":false,"hp":false,"pm":false,"mt":false,"tr":false,"ac":false,"tp":false},{"t":176.343,"s":1,"f":2,"sus":0.0,"sl":-1,"slu":-1,"bn":0,"ho":false,"po":false,"hm":false,"hp":false,"pm":false,"mt":false,"tr":false,"ac":false,"tp":false},{"t":176.588,"s":1,"f":2,"sus":0.0,"sl":-1,"slu":-1,"bn":0,"ho":false,"po":false,"hm":false,"hp":false,"pm":false,"mt":false,"tr":false,"ac":false,"tp":false},{"t":177.078,"s":1,"f":5,"sus":0.0,"sl":-1,"slu":-1,"bn":0,"ho":false,"po":false,"hm":false,"hp":false,"pm":false,"mt":false,"tr":false,"ac":false,"tp":false},{"t":177.57,"s":1,"f":5,"sus":0.0,"sl":-1,"slu":-1,"bn":0,"ho":false,"po":false,"hm":false,"hp":false,"pm":false,"mt":false,"tr":false,"ac":false,"tp":false},{"t":177.819,"s":1,"f":5,"sus":0.0,"sl":-1,"slu":-1,"bn":0,"ho":false,"po":false,"hm":false,"hp":false,"pm":false,"mt":false,"tr":false,"ac":false,"tp":false},{"t":178.319,"s":1,"f":5,"sus":0.0,"sl":-1,"slu":-1,"bn":0,"ho":false,"po":false,"hm":false,"hp":false,"pm":false,"mt":false,"tr":false,"ac":false,"tp":false},{"t":178.557,"s":1,"f":3,"sus":0.0,"sl":-1,"slu":-1,"bn":0,"ho":false,"po":false,"hm":false,"hp":false,"pm":false,"mt":false,"tr":false,"ac":false,"tp":false},{"t":178.795,"s":1,"f":0,"sus":0.0,"sl":-1,"slu":-1,"bn":0,"ho":false,"po":false,"hm":false,"hp":false,"pm":false,"mt":false,"tr":false,"ac":false,"tp":false},{"t":179.033,"s":1,"f":2,"sus":0.0,"sl":-1,"slu":-1,"bn":0,"ho":false,"po":false,"hm":false,"hp":false,"pm":false,"mt":false,"tr":false,"ac":false,"tp":false},{"t":179.523,"s":1,"f":2,"sus":0.0,"sl":-1,"slu":-1,"bn":0,"ho":false,"po":false,"hm":false,"hp":false,"pm":false,"mt":false,"tr":false,"ac":false,"tp":false},{"t":179.768,"s":1,"f":2,"sus":0.0,"sl":-1,"slu":-1,"bn":0,"ho":false,"po":false,"hm":false,"hp":false,"pm":false,"mt":false,"tr":false,"ac":false,"tp":false},{"t":180.262,"s":1,"f":2,"sus":0.0,"sl":-1,"slu":-1,"bn":0,"ho":false,"po":false,"hm":false,"hp":false,"pm":false,"mt":false,"tr":false,"ac":false,"tp":false},{"t":180.509,"s":1,"f":2,"sus":0.0,"sl":-1,"slu":-1,"bn":0,"ho":false,"po":false,"hm":false,"hp":false,"pm":false,"mt":false,"tr":false,"ac":false,"tp":false},{"t":180.754,"s":1,"f":4,"sus":0.0,"sl":-1,"slu":-1,"bn":0,"ho":false,"po":false,"hm":false,"hp":false,"pm":false,"mt":false,"tr":false,"ac":false,"tp":false},{"t":181.0,"s":1,"f":5,"sus":0.002,"sl":-1,"slu":-1,"bn":0,"ho":false,"po":false,"hm":false,"hp":false,"pm":false,"mt":false,"tr":false,"ac":false,"tp":false},{"t":181.493,"s":1,"f":5,"sus":0.0,"sl":-1,"slu":-1,"bn":0,"ho":false,"po":false,"hm":false,"hp":false,"pm":false,"mt":false,"tr":false,"ac":false,"tp":false},{"t":181.733,"s":1,"f":5,"sus":0.0,"sl":-1,"slu":-1,"bn":0,"ho":false,"po":false,"hm":false,"hp":false,"pm":false,"mt":false,"tr":false,"ac":false,"tp":false},{"t":182.196,"s":1,"f":5,"sus":0.0,"sl":-1,"slu":-1,"bn":0,"ho":false,"po":false,"hm":false,"hp":false,"pm":false,"mt":false,"tr":false,"ac":false,"tp":false},{"t":182.436,"s":1,"f":3,"sus":0.0,"sl":-1,"slu":-1,"bn":0,"ho":false,"po":false,"hm":false,"hp":false,"pm":false,"mt":false,"tr":false,"ac":false,"tp":false},{"t":182.671,"s":1,"f":0,"sus":0.0,"sl":-1,"slu":-1,"bn":0,"ho":false,"po":false,"hm":false,"hp":false,"pm":false,"mt":false,"tr":false,"ac":false,"tp":false},{"t":182.911,"s":1,"f":2,"sus":0.002,"sl":-1,"slu":-1,"bn":0,"ho":false,"po":false,"hm":false,"hp":false,"pm":false,"mt":false,"tr":false,"ac":false,"tp":false},{"t":183.407,"s":1,"f":2,"sus":0.0,"sl":-1,"slu":-1,"bn":0,"ho":false,"po":false,"hm":false,"hp":false,"pm":false,"mt":false,"tr":false,"ac":false,"tp":false},{"t":183.657,"s":1,"f":2,"sus":0.002,"sl":-1,"slu":-1,"bn":0,"ho":false,"po":false,"hm":false,"hp":false,"pm":false,"mt":false,"tr":false,"ac":false,"tp":false},{"t":184.162,"s":1,"f":2,"sus":0.002,"sl":-1,"slu":-1,"bn":0,"ho":false,"po":false,"hm":false,"hp":false,"pm":false,"mt":false,"tr":false,"ac":false,"tp":false},{"t":184.421,"s":1,"f":2,"sus":0.002,"sl":-1,"slu":-1,"bn":0,"ho":false,"po":false,"hm":false,"hp":false,"pm":false,"mt":false,"tr":false,"ac":false,"tp":false},{"t":184.659,"s":1,"f":4,"sus":0.0,"sl":-1,"slu":-1,"bn":0,"ho":false,"po":false,"hm":false,"hp":false,"pm":false,"mt":false,"tr":false,"ac":false,"tp":false},{"t":184.874,"s":1,"f":5,"sus":0.0,"sl":-1,"slu":-1,"bn":0,"ho":false,"po":false,"hm":false,"hp":false,"pm":false,"mt":false,"tr":false,"ac":false,"tp":false},{"t":185.338,"s":1,"f":5,"sus":0.002,"sl":-1,"slu":-1,"bn":0,"ho":false,"po":false,"hm":false,"hp":false,"pm":false,"mt":false,"tr":false,"ac":false,"tp":false},{"t":185.589,"s":1,"f":5,"sus":0.0,"sl":-1,"slu":-1,"bn":0,"ho":false,"po":false,"hm":false,"hp":false,"pm":false,"mt":false,"tr":false,"ac":false,"tp":false},{"t":186.092,"s":1,"f":5,"sus":0.0,"sl":-1,"slu":-1,"bn":0,"ho":false,"po":false,"hm":false,"hp":false,"pm":false,"mt":false,"tr":false,"ac":false,"tp":false},{"t":186.371,"s":1,"f":3,"sus":0.0,"sl":-1,"slu":-1,"bn":0,"ho":false,"po":false,"hm":false,"hp":false,"pm":false,"mt":false,"tr":false,"ac":false,"tp":false},{"t":186.645,"s":1,"f":0,"sus":0.0,"sl":-1,"slu":-1,"bn":0,"ho":false,"po":false,"hm":false,"hp":false,"pm":false,"mt":false,"tr":false,"ac":false,"tp":false},{"t":186.92,"s":1,"f":2,"sus":0.0,"sl":-1,"slu":-1,"bn":0,"ho":false,"po":false,"hm":false,"hp":false,"pm":false,"mt":false,"tr":false,"ac":false,"tp":false},{"t":187.481,"s":1,"f":2,"sus":0.0,"sl":-1,"slu":-1,"bn":0,"ho":false,"po":false,"hm":false,"hp":false,"pm":false,"mt":false,"tr":false,"ac":false,"tp":false},{"t":187.759,"s":1,"f":2,"sus":0.002,"sl":-1,"slu":-1,"bn":0,"ho":false,"po":false,"hm":false,"hp":false,"pm":false,"mt":false,"tr":false,"ac":false,"tp":false},{"t":188.301,"s":1,"f":2,"sus":0.0,"sl":-1,"slu":-1,"bn":0,"ho":false,"po":false,"hm":false,"hp":false,"pm":false,"mt":false,"tr":false,"ac":false,"tp":false},{"t":188.551,"s":1,"f":2,"sus":0.0,"sl":-1,"slu":-1,"bn":0,"ho":false,"po":false,"hm":false,"hp":false,"pm":false,"mt":false,"tr":false,"ac":false,"tp":false},{"t":188.767,"s":1,"f":4,"sus":0.0,"sl":-1,"slu":-1,"bn":0,"ho":false,"po":false,"hm":false,"hp":false,"pm":false,"mt":false,"tr":false,"ac":false,"tp":false},{"t":188.949,"s":1,"f":5,"sus":0.0,"sl":-1,"slu":-1,"bn":0,"ho":false,"po":false,"hm":false,"hp":false,"pm":false,"mt":false,"tr":false,"ac":false,"tp":false},{"t":189.517,"s":1,"f":5,"sus":0.0,"sl":-1,"slu":-1,"bn":0,"ho":false,"po":false,"hm":false,"hp":false,"pm":false,"mt":false,"tr":false,"ac":false,"tp":false},{"t":189.793,"s":1,"f":5,"sus":0.0,"sl":-1,"slu":-1,"bn":0,"ho":false,"po":false,"hm":false,"hp":false,"pm":false,"mt":false,"tr":false,"ac":false,"tp":false},{"t":190.261,"s":1,"f":5,"sus":0.0,"sl":-1,"slu":-1,"bn":0,"ho":false,"po":false,"hm":false,"hp":false,"pm":false,"mt":false,"tr":false,"ac":false,"tp":false},{"t":190.495,"s":1,"f":3,"sus":0.0,"sl":-1,"slu":-1,"bn":0,"ho":false,"po":false,"hm":false,"hp":false,"pm":false,"mt":false,"tr":false,"ac":false,"tp":false},{"t":190.731,"s":1,"f":0,"sus":0.0,"sl":-1,"slu":-1,"bn":0,"ho":false,"po":false,"hm":false,"hp":false,"pm":false,"mt":false,"tr":false,"ac":false,"tp":false},{"t":190.969,"s":1,"f":2,"sus":0.0,"sl":-1,"slu":-1,"bn":0,"ho":false,"po":false,"hm":false,"hp":false,"pm":false,"mt":false,"tr":false,"ac":false,"tp":false},{"t":191.445,"s":1,"f":2,"sus":0.0,"sl":-1,"slu":-1,"bn":0,"ho":false,"po":false,"hm":false,"hp":false,"pm":false,"mt":false,"tr":false,"ac":false,"tp":false},{"t":191.689,"s":1,"f":2,"sus":0.0,"sl":-1,"slu":-1,"bn":0,"ho":false,"po":false,"hm":false,"hp":false,"pm":false,"mt":false,"tr":false,"ac":false,"tp":false},{"t":192.173,"s":1,"f":2,"sus":0.0,"sl":-1,"slu":-1,"bn":0,"ho":false,"po":false,"hm":false,"hp":false,"pm":false,"mt":false,"tr":false,"ac":false,"tp":false},{"t":192.39,"s":1,"f":2,"sus":0.0,"sl":-1,"slu":-1,"bn":0,"ho":false,"po":false,"hm":false,"hp":false,"pm":false,"mt":false,"tr":false,"ac":false,"tp":false},{"t":192.607,"s":1,"f":4,"sus":0.0,"sl":-1,"slu":-1,"bn":0,"ho":false,"po":false,"hm":false,"hp":false,"pm":false,"mt":false,"tr":false,"ac":false,"tp":false},{"t":192.824,"s":1,"f":5,"sus":0.0,"sl":-1,"slu":-1,"bn":0,"ho":false,"po":false,"hm":false,"hp":false,"pm":false,"mt":false,"tr":false,"ac":false,"tp":false},{"t":193.041,"s":1,"f":5,"sus":0.0,"sl":-1,"slu":-1,"bn":0,"ho":false,"po":false,"hm":false,"hp":false,"pm":false,"mt":false,"tr":false,"ac":false,"tp":false},{"t":193.258,"s":1,"f":5,"sus":0.0,"sl":-1,"slu":-1,"bn":0,"ho":false,"po":false,"hm":false,"hp":false,"pm":false,"mt":false,"tr":false,"ac":false,"tp":false},{"t":193.475,"s":1,"f":5,"sus":0.0,"sl":-1,"slu":-1,"bn":0,"ho":false,"po":false,"hm":false,"hp":false,"pm":false,"mt":false,"tr":false,"ac":false,"tp":false},{"t":193.925,"s":1,"f":7,"sus":0.0,"sl":-1,"slu":-1,"bn":0,"ho":false,"po":false,"hm":false,"hp":false,"pm":false,"mt":false,"tr":false,"ac":false,"tp":false},{"t":194.175,"s":1,"f":7,"sus":0.0,"sl":-1,"slu":-1,"bn":0,"ho":false,"po":false,"hm":false,"hp":false,"pm":false,"mt":false,"tr":false,"ac":false,"tp":false},{"t":194.425,"s":1,"f":8,"sus":0.0,"sl":-1,"slu":-1,"bn":0,"ho":false,"po":false,"hm":false,"hp":false,"pm":false,"mt":false,"tr":false,"ac":false,"tp":false},{"t":194.675,"s":1,"f":9,"sus":0.437,"sl":-1,"slu":-1,"bn":0,"ho":false,"po":false,"hm":false,"hp":false,"pm":false,"mt":false,"tr":false,"ac":false,"tp":false},{"t":195.115,"s":2,"f":7,"sus":0.0,"sl":-1,"slu":-1,"bn":0,"ho":false,"po":false,"hm":false,"hp":false,"pm":false,"mt":false,"tr":false,"ac":false,"tp":false},{"t":195.344,"s":1,"f":9,"sus":0.0,"sl":-1,"slu":-1,"bn":0,"ho":false,"po":false,"hm":false,"hp":false,"pm":false,"mt":false,"tr":false,"ac":false,"tp":false},{"t":195.593,"s":2,"f":7,"sus":0.0,"sl":-1,"slu":-1,"bn":0,"ho":false,"po":false,"hm":false,"hp":false,"pm":false,"mt":false,"tr":false,"ac":false,"tp":false},{"t":195.841,"s":1,"f":9,"sus":0.0,"sl":-1,"slu":-1,"bn":0,"ho":false,"po":false,"hm":false,"hp":false,"pm":false,"mt":false,"tr":false,"ac":false,"tp":false},{"t":196.09,"s":1,"f":9,"sus":0.0,"sl":-1,"slu":-1,"bn":0,"ho":false,"po":false,"hm":false,"hp":false,"pm":false,"mt":false,"tr":false,"ac":false,"tp":false},{"t":196.338,"s":1,"f":8,"sus":0.0,"sl":-1,"slu":-1,"bn":0,"ho":false,"po":false,"hm":false,"hp":false,"pm":false,"mt":false,"tr":false,"ac":false,"tp":false},{"t":196.587,"s":1,"f":7,"sus":0.0,"sl":-1,"slu":-1,"bn":0,"ho":false,"po":false,"hm":false,"hp":false,"pm":false,"mt":false,"tr":false,"ac":false,"tp":false},{"t":196.836,"s":2,"f":9,"sus":0.0,"sl":-1,"slu":-1,"bn":0,"ho":false,"po":false,"hm":false,"hp":false,"pm":false,"mt":false,"tr":false,"ac":false,"tp":false},{"t":197.084,"s":1,"f":7,"sus":0.0,"sl":-1,"slu":-1,"bn":0,"ho":false,"po":false,"hm":false,"hp":false,"pm":false,"mt":false,"tr":false,"ac":false,"tp":false},{"t":197.333,"s":1,"f":7,"sus":0.494,"sl":-1,"slu":-1,"bn":0,"ho":false,"po":false,"hm":false,"hp":false,"pm":false,"mt":false,"tr":false,"ac":false,"tp":false},{"t":197.83,"s":2,"f":9,"sus":0.0,"sl":-1,"slu":-1,"bn":0,"ho":false,"po":false,"hm":false,"hp":false,"pm":false,"mt":false,"tr":false,"ac":false,"tp":false},{"t":198.079,"s":1,"f":7,"sus":0.0,"sl":-1,"slu":-1,"bn":0,"ho":false,"po":false,"hm":false,"hp":false,"pm":false,"mt":false,"tr":false,"ac":false,"tp":false},{"t":198.327,"s":1,"f":8,"sus":0.0,"sl":-1,"slu":-1,"bn":0,"ho":false,"po":false,"hm":false,"hp":false,"pm":false,"mt":false,"tr":false,"ac":false,"tp":false},{"t":198.575,"s":1,"f":9,"sus":0.494,"sl":-1,"slu":-1,"bn":0,"ho":false,"po":false,"hm":false,"hp":false,"pm":false,"mt":false,"tr":false,"ac":false,"tp":false},{"t":199.072,"s":2,"f":7,"sus":0.0,"sl":-1,"slu":-1,"bn":0,"ho":false,"po":false,"hm":false,"hp":false,"pm":false,"mt":false,"tr":false,"ac":false,"tp":false},{"t":199.321,"s":1,"f":9,"sus":0.0,"sl":-1,"slu":-1,"bn":0,"ho":false,"po":false,"hm":false,"hp":false,"pm":false,"mt":false,"tr":false,"ac":false,"tp":false},{"t":199.569,"s":2,"f":7,"sus":0.0,"sl":-1,"slu":-1,"bn":0,"ho":false,"po":false,"hm":false,"hp":false,"pm":false,"mt":false,"tr":false,"ac":false,"tp":false},{"t":199.818,"s":1,"f":9,"sus":0.0,"sl":-1,"slu":-1,"bn":0,"ho":false,"po":false,"hm":false,"hp":false,"pm":false,"mt":false,"tr":false,"ac":false,"tp":false},{"t":200.067,"s":1,"f":9,"sus":0.0,"sl":-1,"slu":-1,"bn":0,"ho":false,"po":false,"hm":false,"hp":false,"pm":false,"mt":false,"tr":false,"ac":false,"tp":false},{"t":200.315,"s":1,"f":8,"sus":0.0,"sl":-1,"slu":-1,"bn":0,"ho":false,"po":false,"hm":false,"hp":false,"pm":false,"mt":false,"tr":false,"ac":false,"tp":false},{"t":200.564,"s":1,"f":7,"sus":0.0,"sl":-1,"slu":-1,"bn":0,"ho":false,"po":false,"hm":false,"hp":false,"pm":false,"mt":false,"tr":false,"ac":false,"tp":false},{"t":200.803,"s":2,"f":9,"sus":0.0,"sl":-1,"slu":-1,"bn":0,"ho":false,"po":false,"hm":false,"hp":false,"pm":false,"mt":false,"tr":false,"ac":false,"tp":false},{"t":201.033,"s":1,"f":7,"sus":0.0,"sl":-1,"slu":-1,"bn":0,"ho":false,"po":false,"hm":false,"hp":false,"pm":false,"mt":false,"tr":false,"ac":false,"tp":false},{"t":201.271,"s":1,"f":7,"sus":0.489,"sl":-1,"slu":-1,"bn":0,"ho":false,"po":false,"hm":false,"hp":false,"pm":false,"mt":false,"tr":false,"ac":false,"tp":false},{"t":201.763,"s":2,"f":9,"sus":0.0,"sl":-1,"slu":-1,"bn":0,"ho":false,"po":false,"hm":false,"hp":false,"pm":false,"mt":false,"tr":false,"ac":false,"tp":false},{"t":202.009,"s":1,"f":7,"sus":0.0,"sl":-1,"slu":-1,"bn":0,"ho":false,"po":false,"hm":false,"hp":false,"pm":false,"mt":false,"tr":false,"ac":false,"tp":false},{"t":202.255,"s":1,"f":8,"sus":0.0,"sl":-1,"slu":-1,"bn":0,"ho":false,"po":false,"hm":false,"hp":false,"pm":false,"mt":false,"tr":false,"ac":false,"tp":false},{"t":202.501,"s":1,"f":9,"sus":0.489,"sl":-1,"slu":-1,"bn":0,"ho":false,"po":false,"hm":false,"hp":false,"pm":false,"mt":false,"tr":false,"ac":false,"tp":false},{"t":202.993,"s":2,"f":7,"sus":0.0,"sl":-1,"slu":-1,"bn":0,"ho":false,"po":false,"hm":false,"hp":false,"pm":false,"mt":false,"tr":false,"ac":false,"tp":false},{"t":203.239,"s":1,"f":9,"sus":0.0,"sl":-1,"slu":-1,"bn":0,"ho":false,"po":false,"hm":false,"hp":false,"pm":false,"mt":false,"tr":false,"ac":false,"tp":false},{"t":203.485,"s":2,"f":7,"sus":0.0,"sl":-1,"slu":-1,"bn":0,"ho":false,"po":false,"hm":false,"hp":false,"pm":false,"mt":false,"tr":false,"ac":false,"tp":false},{"t":203.731,"s":1,"f":9,"sus":0.0,"sl":-1,"slu":-1,"bn":0,"ho":false,"po":false,"hm":false,"hp":false,"pm":false,"mt":false,"tr":false,"ac":false,"tp":false},{"t":203.977,"s":1,"f":9,"sus":0.0,"sl":-1,"slu":-1,"bn":0,"ho":false,"po":false,"hm":false,"hp":false,"pm":false,"mt":false,"tr":false,"ac":false,"tp":false},{"t":204.223,"s":1,"f":8,"sus":0.0,"sl":-1,"slu":-1,"bn":0,"ho":false,"po":false,"hm":false,"hp":false,"pm":false,"mt":false,"tr":false,"ac":false,"tp":false},{"t":204.469,"s":1,"f":7,"sus":0.0,"sl":-1,"slu":-1,"bn":0,"ho":false,"po":false,"hm":false,"hp":false,"pm":false,"mt":false,"tr":false,"ac":false,"tp":false},{"t":204.715,"s":2,"f":9,"sus":0.0,"sl":-1,"slu":-1,"bn":0,"ho":false,"po":false,"hm":false,"hp":false,"pm":false,"mt":false,"tr":false,"ac":false,"tp":false},{"t":204.961,"s":1,"f":7,"sus":0.0,"sl":-1,"slu":-1,"bn":0,"ho":false,"po":false,"hm":false,"hp":false,"pm":false,"mt":false,"tr":false,"ac":false,"tp":false},{"t":205.207,"s":1,"f":7,"sus":0.487,"sl":-1,"slu":-1,"bn":0,"ho":false,"po":false,"hm":false,"hp":false,"pm":false,"mt":false,"tr":false,"ac":false,"tp":false},{"t":205.697,"s":2,"f":9,"sus":0.002,"sl":-1,"slu":-1,"bn":0,"ho":false,"po":false,"hm":false,"hp":false,"pm":false,"mt":false,"tr":false,"ac":false,"tp":false},{"t":205.94,"s":1,"f":7,"sus":0.002,"sl":-1,"slu":-1,"bn":0,"ho":false,"po":false,"hm":false,"hp":false,"pm":false,"mt":false,"tr":false,"ac":false,"tp":false},{"t":206.183,"s":1,"f":8,"sus":0.002,"sl":-1,"slu":-1,"bn":0,"ho":false,"po":false,"hm":false,"hp":false,"pm":false,"mt":false,"tr":false,"ac":false,"tp":false},{"t":206.426,"s":1,"f":9,"sus":0.483,"sl":-1,"slu":-1,"bn":0,"ho":false,"po":false,"hm":false,"hp":false,"pm":false,"mt":false,"tr":false,"ac":false,"tp":false},{"t":206.912,"s":2,"f":7,"sus":0.002,"sl":-1,"slu":-1,"bn":0,"ho":false,"po":false,"hm":false,"hp":false,"pm":false,"mt":false,"tr":false,"ac":false,"tp":false},{"t":207.155,"s":1,"f":9,"sus":0.002,"sl":-1,"slu":-1,"bn":0,"ho":false,"po":false,"hm":false,"hp":false,"pm":false,"mt":false,"tr":false,"ac":false,"tp":false},{"t":207.398,"s":2,"f":7,"sus":0.002,"sl":-1,"slu":-1,"bn":0,"ho":false,"po":false,"hm":false,"hp":false,"pm":false,"mt":false,"tr":false,"ac":false,"tp":false},{"t":207.642,"s":1,"f":9,"sus":0.0,"sl":-1,"slu":-1,"bn":0,"ho":false,"po":false,"hm":false,"hp":false,"pm":false,"mt":false,"tr":false,"ac":false,"tp":false},{"t":207.886,"s":1,"f":9,"sus":0.0,"sl":-1,"slu":-1,"bn":0,"ho":false,"po":false,"hm":false,"hp":false,"pm":false,"mt":false,"tr":false,"ac":false,"tp":false},{"t":208.13,"s":1,"f":8,"sus":0.0,"sl":-1,"slu":-1,"bn":0,"ho":false,"po":false,"hm":false,"hp":false,"pm":false,"mt":false,"tr":false,"ac":false,"tp":false},{"t":208.374,"s":1,"f":7,"sus":0.0,"sl":-1,"slu":-1,"bn":0,"ho":false,"po":false,"hm":false,"hp":false,"pm":false,"mt":false,"tr":false,"ac":false,"tp":false},{"t":208.621,"s":2,"f":9,"sus":0.0,"sl":-1,"slu":-1,"bn":0,"ho":false,"po":false,"hm":false,"hp":false,"pm":false,"mt":false,"tr":false,"ac":false,"tp":false},{"t":208.871,"s":1,"f":7,"sus":0.0,"sl":-1,"slu":-1,"bn":0,"ho":false,"po":false,"hm":false,"hp":false,"pm":false,"mt":false,"tr":false,"ac":false,"tp":false},{"t":209.121,"s":1,"f":7,"sus":0.497,"sl":-1,"slu":-1,"bn":0,"ho":false,"po":false,"hm":false,"hp":false,"pm":false,"mt":false,"tr":false,"ac":false,"tp":false},{"t":209.621,"s":2,"f":9,"sus":0.0,"sl":-1,"slu":-1,"bn":0,"ho":false,"po":false,"hm":false,"hp":false,"pm":false,"mt":false,"tr":false,"ac":false,"tp":false},{"t":209.871,"s":1,"f":7,"sus":0.0,"sl":-1,"slu":-1,"bn":0,"ho":false,"po":false,"hm":false,"hp":false,"pm":false,"mt":false,"tr":false,"ac":false,"tp":false},{"t":210.121,"s":1,"f":8,"sus":0.0,"sl":-1,"slu":-1,"bn":0,"ho":false,"po":false,"hm":false,"hp":false,"pm":false,"mt":false,"tr":false,"ac":false,"tp":false},{"t":210.371,"s":1,"f":9,"sus":6.0,"sl":-1,"slu":-1,"bn":0,"ho":false,"po":false,"hm":false,"hp":false,"pm":false,"mt":false,"tr":false,"ac":false,"tp":false}],"chords":[],"anchors":[{"time":11.427,"fret":7,"width":4},{"time":20.703,"fret":7,"width":4},{"time":50.905,"fret":7,"width":4},{"time":52.106,"fret":2,"width":4},{"time":67.601,"fret":7,"width":4},{"time":68.627,"fret":7,"width":4},{"time":82.937,"fret":7,"width":4},{"time":84.187,"fret":2,"width":4},{"time":101.262,"fret":2,"width":4},{"time":115.285,"fret":7,"width":4},{"time":123.189,"fret":7,"width":4},{"time":155.259,"fret":2,"width":4},{"time":156.009,"fret":2,"width":4},{"time":171.193,"fret":2,"width":4},{"time":193.925,"fret":7,"width":4}],"handshapes":[],"templates":[]}